{"manifest":"m343296","canvas":"https:\/\/digitalcollections.universiteitleiden.nl\/iiif_manifest\/item:343307\/canvas\/default","page":"ᰣᰫ ᰋᰦ ᰍᰦᰮ ᰠ ᰌᰪᰳ ᰕᰫᰵ ᰂᰦᰰ ᰡᰦᰵ [1] ᰌᰧ ᰢᰩ ᰀ ᰚᰦᰮ ᰕᰦ ᰣᰨ ᰼ ᰊᰪᰭ ᰓᰨ ᰋᰧᰵᰶ [2] ᰍᰪᰰ ᰎ ᰍᰨ ᰣᰪᰲ ᰛᰬ ᰇᰨ ᰠ ᰝᰤᰪᰮᰶ ᰀᰦ ᰋᰦᰱ [3] ᰜᰬᰯ ᰜᰪᰵ ᰠᰪᰵ ᰼ ᰣᰤᰦ ᰣᰨ ᰋᰦ ᰍᰦᰮ [4] ᰠ ᰎᰪᰰ ᰌᰧ ᰊᰧᰮᰶ ᰓᰨ ᰛᰬ ᰛᰪᰮ ᰕᰧᰳᰶ ᰍᰨᰲ ᰕᰧᰳᰶ [5] ᰀ ᰚᰦᰮ ᰕ ᰣᰨ ᰼ ᰣᰨ ᰋᰦ ᰍᰦᰮ ᰠ ᰀᰪᰲ [6] ᰋᰦᰭ ᰢᰨᰭ ᰛᰬ ᰊᰧᰮᰶ ᰓᰨ ᰛᰬ ᰊᰪᰭ ᰓᰨ ᰠ ᰣᰦ [7] ᰃᰤᰬᰰ ᰀᰪᰱ ᰃᰪᰮ ᰌᰧᰭᰶ ᰎᰫ ᰠ ᰎ ᰍᰨ ᰊᰧᰮᰶ [8] ᰓᰨ ᰃᰥᰦᰵ ᰌᰧ ᰢᰦ ᰕᰪᰮ ᰼ ᰀᰪᰲ ᰋᰦᰭ [9] ᰊᰧᰮᰶ ᰓᰨ ᰢᰨᰭ ᰛᰬ ᰍᰪᰰ ᰊᰤᰪᰳ ᰜᰬᰯ ᰜᰪᰵ ᰠ [10] ᰇᰨ ᰠ ᰊᰰᰶ ᰃᰪᰰ ᰍ ᰛᰪᰱ ᰜᰬᰯ ᰜᰪᰵ ᰠ [11] ","annotations":[{"manifest":"m343296","canvas":"https:\/\/digitalcollections.universiteitleiden.nl\/iiif_manifest\/item:343307\/canvas\/default","mode":"line","line":"1","annotation":{"id":"https:\/\/digitalcollections.universiteitleiden.nl\/iiif_manifest\/item:343307\/canvas\/default\/annotation\/r1o","type":"Annotation","motivation":"supplementing","body":{"text":"ᰣᰫ ᰋᰦ ᰍᰦᰮ ᰠ ᰌᰪᰳ ᰕᰫᰵ ᰂᰦᰰ ᰡᰦᰵ","type":"TextualBody"},"target":"https:\/\/digitalcollections.universiteitleiden.nl\/iiif_manifest\/item:343307\/canvas\/default#xywh=2640,317,1405,137"}},{"manifest":"m343296","canvas":"https:\/\/digitalcollections.universiteitleiden.nl\/iiif_manifest\/item:343307\/canvas\/default","mode":"line","line":"2","annotation":{"id":"https:\/\/digitalcollections.universiteitleiden.nl\/iiif_manifest\/item:343307\/canvas\/default\/annotation\/r2o","type":"Annotation","motivation":"supplementing","body":{"text":"ᰌᰧ ᰢᰩ ᰀ ᰚᰦᰮ ᰕᰦ ᰣᰨ ᰼ ᰊᰪᰭ ᰓᰨ ᰋᰧᰵᰶ","type":"TextualBody"},"target":"https:\/\/digitalcollections.universiteitleiden.nl\/iiif_manifest\/item:343307\/canvas\/default#xywh=2689,511,1380,156"}},{"manifest":"m343296","canvas":"https:\/\/digitalcollections.universiteitleiden.nl\/iiif_manifest\/item:343307\/canvas\/default","mode":"line","line":"3","annotation":{"id":"https:\/\/digitalcollections.universiteitleiden.nl\/iiif_manifest\/item:343307\/canvas\/default\/annotation\/r3o","type":"Annotation","motivation":"supplementing","body":{"text":"ᰍᰪᰰ ᰎ ᰍᰨ ᰣᰪᰲ ᰛᰬ ᰇᰨ ᰠ ᰝᰤᰪᰮᰶ ᰀᰦ ᰋᰦᰱ","type":"TextualBody"},"target":"https:\/\/digitalcollections.universiteitleiden.nl\/iiif_manifest\/item:343307\/canvas\/default#xywh=2678,715,1398,156"}},{"manifest":"m343296","canvas":"https:\/\/digitalcollections.universiteitleiden.nl\/iiif_manifest\/item:343307\/canvas\/default","mode":"line","line":"4","annotation":{"id":"https:\/\/digitalcollections.universiteitleiden.nl\/iiif_manifest\/item:343307\/canvas\/default\/annotation\/r4o","type":"Annotation","motivation":"supplementing","body":{"text":"ᰜᰬᰯ ᰜᰪᰵ ᰠᰪᰵ ᰼ ᰣᰤᰦ ᰣᰨ ᰋᰦ ᰍᰦᰮ","type":"TextualBody"},"target":"https:\/\/digitalcollections.universiteitleiden.nl\/iiif_manifest\/item:343307\/canvas\/default#xywh=2698,923,1344,130"}},{"manifest":"m343296","canvas":"https:\/\/digitalcollections.universiteitleiden.nl\/iiif_manifest\/item:343307\/canvas\/default","mode":"line","line":"5","annotation":{"id":"https:\/\/digitalcollections.universiteitleiden.nl\/iiif_manifest\/item:343307\/canvas\/default\/annotation\/r5o","type":"Annotation","motivation":"supplementing","body":{"text":"ᰠ ᰎᰪᰰ ᰌᰧ ᰊᰧᰮᰶ ᰓᰨ ᰛᰬ ᰛᰪᰮ ᰕᰧᰳᰶ ᰍᰨᰲ ᰕᰧᰳᰶ","type":"TextualBody"},"target":"https:\/\/digitalcollections.universiteitleiden.nl\/iiif_manifest\/item:343307\/canvas\/default#xywh=2727,1120,1358,150"}},{"manifest":"m343296","canvas":"https:\/\/digitalcollections.universiteitleiden.nl\/iiif_manifest\/item:343307\/canvas\/default","mode":"line","line":"6","annotation":{"id":"https:\/\/digitalcollections.universiteitleiden.nl\/iiif_manifest\/item:343307\/canvas\/default\/annotation\/r6o","type":"Annotation","motivation":"supplementing","body":{"text":"ᰀ ᰚᰦᰮ ᰕ ᰣᰨ ᰼ ᰣᰨ ᰋᰦ ᰍᰦᰮ ᰠ ᰀᰪᰲ","type":"TextualBody"},"target":"https:\/\/digitalcollections.universiteitleiden.nl\/iiif_manifest\/item:343307\/canvas\/default#xywh=2734,1323,1321,153"}},{"manifest":"m343296","canvas":"https:\/\/digitalcollections.universiteitleiden.nl\/iiif_manifest\/item:343307\/canvas\/default","mode":"line","line":"7","annotation":{"id":"https:\/\/digitalcollections.universiteitleiden.nl\/iiif_manifest\/item:343307\/canvas\/default\/annotation\/r7o","type":"Annotation","motivation":"supplementing","body":{"text":"ᰋᰦᰭ ᰢᰨᰭ ᰛᰬ ᰊᰧᰮᰶ ᰓᰨ ᰛᰬ ᰊᰪᰭ ᰓᰨ ᰠ ᰣᰦ","type":"TextualBody"},"target":"https:\/\/digitalcollections.universiteitleiden.nl\/iiif_manifest\/item:343307\/canvas\/default#xywh=2786,1535,1292,133"}},{"manifest":"m343296","canvas":"https:\/\/digitalcollections.universiteitleiden.nl\/iiif_manifest\/item:343307\/canvas\/default","mode":"line","line":"8","annotation":{"id":"https:\/\/digitalcollections.universiteitleiden.nl\/iiif_manifest\/item:343307\/canvas\/default\/annotation\/r8o","type":"Annotation","motivation":"supplementing","body":{"text":"ᰃᰤᰬᰰ ᰀᰪᰱ ᰃᰪᰮ ᰌᰧᰭᰶ ᰎᰫ ᰠ ᰎ ᰍᰨ ᰊᰧᰮᰶ","type":"TextualBody"},"target":"https:\/\/digitalcollections.universiteitleiden.nl\/iiif_manifest\/item:343307\/canvas\/default#xywh=2779,1747,1272,124"}},{"manifest":"m343296","canvas":"https:\/\/digitalcollections.universiteitleiden.nl\/iiif_manifest\/item:343307\/canvas\/default","mode":"line","line":"9","annotation":{"id":"https:\/\/digitalcollections.universiteitleiden.nl\/iiif_manifest\/item:343307\/canvas\/default\/annotation\/r9o","type":"Annotation","motivation":"supplementing","body":{"text":"ᰓᰨ ᰃᰥᰦᰵ ᰌᰧ ᰢᰦ ᰕᰪᰮ ᰼ ᰀᰪᰲ ᰋᰦᰭ","type":"TextualBody"},"target":"https:\/\/digitalcollections.universiteitleiden.nl\/iiif_manifest\/item:343307\/canvas\/default#xywh=2692,1947,1368,132"}},{"manifest":"m343296","canvas":"https:\/\/digitalcollections.universiteitleiden.nl\/iiif_manifest\/item:343307\/canvas\/default","mode":"line","line":"10","annotation":{"id":"https:\/\/digitalcollections.universiteitleiden.nl\/iiif_manifest\/item:343307\/canvas\/default\/annotation\/r10o","type":"Annotation","motivation":"supplementing","body":{"text":"ᰊᰧᰮᰶ ᰓᰨ ᰢᰨᰭ ᰛᰬ ᰍᰪᰰ ᰊᰤᰪᰳ ᰜᰬᰯ ᰜᰪᰵ ᰠ","type":"TextualBody"},"target":"https:\/\/digitalcollections.universiteitleiden.nl\/iiif_manifest\/item:343307\/canvas\/default#xywh=2734,2141,1317,146"}},{"manifest":"m343296","canvas":"https:\/\/digitalcollections.universiteitleiden.nl\/iiif_manifest\/item:343307\/canvas\/default","mode":"line","line":"11","annotation":{"id":"https:\/\/digitalcollections.universiteitleiden.nl\/iiif_manifest\/item:343307\/canvas\/default\/annotation\/r11o","type":"Annotation","motivation":"supplementing","body":{"text":"ᰇᰨ ᰠ ᰊᰰᰶ ᰃᰪᰰ ᰍ ᰛᰪᰱ ᰜᰬᰯ ᰜᰪᰵ ᰠ","type":"TextualBody"},"target":"https:\/\/digitalcollections.universiteitleiden.nl\/iiif_manifest\/item:343307\/canvas\/default#xywh=2734,2344,1233,141"}}]}