{"manifest":"m335106","canvas":"https:\/\/digitalcollections.universiteitleiden.nl\/iiif_manifest\/item:335133\/canvas\/default","page":"ᰣᰨ ᰼ ᰣᰬ ᰃᰨ ᰛᰨ ᰜᰪᰵ ᰅᰭᰶ ᰜ ᰕ ᰊᰰᰶ ᰍ ᰃᰴ ᰜ ᰝᰨ ᰡᰦ ᰬ ᰕᰦᰳ ᰌᰤᰦᰵ ᰟᰪᰵ [1] ᰃᰩ ᰚᰴ ᰑᰤᰬᰰᰳ ᰡᰬᰰ ᰜ ᰓᰦ ᰝᰪ ᰍᰪᰰ ᰜᰧ ᰓᰦ ᰊ ᰣᰤᰦ ᰊᰦᰯ ᰜ ᰠᰪᰭ ᰌᰪᰮ ᰜᰦᰵ [2] ᰀᰦ ᰜᰤᰦᰵ ᰣᰫᰵ ᰋᰨ ᰓᰦᰰ ᰀ ᰠᰪᰮ ᰀᰦ ᰕ ᰋᰴ ᰕ ᰉᰧᰰᰶ ᰍᰪᰵ ᰠ ᰀ ᰃᰪᰱ [3] ᰠ ᰕ ᰛᰪᰮ ᰣᰫᰵ ᰀᰦ ᰊᰧᰵᰶ ᰓᰧ ᰎᰦ ᰚᰦᰮ ᰕᰦ ᰣᰨ ᰼ ᰣᰬ ᰣᰨ ᰛᰬ ᰍᰪᰰ ᰙᰨ [4] ᰝᰥᰫᰧ ᰙᰩᰮ ᰜᰪᰵ ᰣᰫᰵ ᰜ ᰉᰩᰮ ᰍᰩᰰ ᰍᰬ ᰚᰦᰮ ᰕᰦ ᰣᰨ ᰼ ᰀᰦ ᰠᰪᰮ ᰠᰩᰳ ᰊᰪᰵ ᰠ [5] ᰣᰦ ᰜᰩᰮᰶ ᰜᰤᰩᰱ ᰕᰦ ᰚᰴ ᰋᰪᰰ ᰜᰧ ᰎᰦ ᰚᰦᰮ ᰕᰦ ᰣᰨ ᰼ ᰀ ᰠᰪᰭ ᰠᰩᰳ ᰓᰦ [6] ᰊᰨ ᰍᰪᰰ ᰜ ᰕ ᰚᰪᰰ ᰍᰬ ᰝᰨ ᰋᰦᰭ ᰕ ᰌᰤᰦᰯ ᰍᰪᰰ ᰣᰨ ᰚᰴ ᰜᰧ ᰎᰦ ᰚᰦᰮ [7] ᰕᰦ ᰣᰨ ᰼ ᰣᰨ ᰛᰬ ᰍᰪᰰ ᰉᰨ ᰃᰧᰵᰶ ᰜᰧ ᰠ ᰌ ᰚᰴ ᰠ ᰌ ᰀᰦ ᰆᰧᰭᰶ [8] ᰍᰩᰰ ᰍᰬ ᰚᰦᰮ ᰕᰦ ᰣᰨ ᰼ ᰣᰨ ᰓᰦ ᰜᰤᰦᰵ ᰀᰦ ᰋᰧ ᰡᰬᰰ ᰜ ᰎᰪᰰ ᰌᰧ ᰀᰳ [9] ᰜᰧ ᰓᰦᰮ ᰉᰧ ᰎᰦ ᰚᰦᰮ ᰕᰦ ᰣᰨ ᰼ ᰝᰪᰮ ᰚᰫ ᰍᰪᰰ ᰜᰧ ᰓᰦ ᰀ ᰚᰫ ᰍ [10] ᰗᰪ ᰀᰤᰬᰳ ᰕ ᰋᰩᰰ ᰍᰬ ᰚᰴ ᰜᰧ ᰜᰪᰵ ᰜᰧ ᰓᰦ ᰣᰨ ᰃᰪᰰ ᰌᰧᰵᰶ ᰍᰩᰰ ᰍᰬ [11] ᰚᰴ ᰜᰧ ᰚᰦᰮ ᰕᰦ ᰣᰨ ᰼ ᰌ ᰜ ᰂᰦᰰ ᰍᰩᰰ ᰍᰬ ᰀ ᰚᰫᰭ ᰀ ᰊᰦ ᰃᰴ [12] ᰎᰦᰰ ᰉᰧ ᰕᰦ ᰚᰦᰮ ᰕᰦ ᰣᰨ ᰼ ᰝᰪᰮ ᰚᰫᰭ ᰍᰪᰰ ᰣ ᰜᰧᰶ ᰓᰦ ᰜᰤᰦᰵ ᰚᰦᰮ ᰓᰨ [13] ᰓᰧᰵᰶ ᰜᰤᰦᰵ ᰠ ᰓᰦ ᰜ ᰃᰪᰰ ᰍ ᰉᰩᰮ ᰍᰩᰰ ᰍᰬ ᰚᰴ ᰜᰧ ᰎᰦ ᰚᰦᰮ ᰕᰦ ᰣᰨ [14] ᰼ ᰕ ᰃᰫᰰ ᰕ ᰃᰤᰦᰰ ᰍᰪᰵ ᰠ ᰠ ᰌᰪᰭ ᰜ ᰀ ᰜᰪᰵ ᰕ ᰛᰩ ᰕᰦᰭ ᰌᰩᰮ ᰉᰧ [15] ᰊᰪᰮ ᰣᰨ ᰚᰴ ᰜᰧ ᰎᰦ ᰚᰦᰮ ᰕᰦ ᰣᰨ ᰼ ᰙ ᰓᰦ ᰃᰴ ᰜ ᰋᰦᰮ ᰓᰨ ᰜᰧᰵᰶ [16] ᰜᰤᰦᰵ ᰣᰦ ᰛᰬ ᰀᰦ ᰕ ᰛᰩ ᰣᰦ ᰀᰪᰱ ᰃᰬᰮᰭ ᰅᰪᰵ ᰎᰴ ᰛᰬ ᰌᰫ ᰌᰩᰮ ᰓᰦᰮ ᰕᰦᰯ [17] ᰀᰦ ᰊᰪᰮ ᰣᰨ ᰚᰴ ᰜᰧ ᰊᰤᰬᰰ ᰀᰦ ᰀ ᰠᰪ ᰠ ᰣᰦ ᰆᰧᰵᰶ ᰉᰪᰮ ᰍᰪᰰ ᰜᰧᰴ [18] ᰓᰦ ᰣᰦ ᰜᰴ ᰃᰪᰮᰶ ᰃᰩᰮᰶ ᰕᰦᰳ ᰍᰦ ᰚᰴ ᰜᰧ ᰢᰪᰵ ᰠ ᰃᰨ ᰠ ᰜᰤᰨᰵ ᰀ ᰀᰪ [19] ᰚᰴ ᰕ ᰉᰧᰰᰶ ᰍᰪᰵ ᰠ ᰀᰦ ᰀᰦ ᰍᰬ ᰌᰦᰮ ᰚᰴ ᰠ ᰜᰤᰦᰵ ᰀᰦ ᰋᰧᰰᰶ ᰓᰦ [20] ᰣᰨ ᰓᰦ ᰠ ᰕ ᰛᰩ ᰌᰨ ᰙᰩᰵ ᰙ ᰌᰤᰪ ᰜᰪᰵ ᰠᰩᰳ ᰓᰪᰭ ᰜᰪᰵ ᰣᰦ ᰕᰬᰰ ᰣᰦ ᰆᰧᰰᰶ [21] ᰋᰴ ᰓᰦᰮ ᰣᰦ ᰃᰨ ᰅᰭᰶ ᰜ ᰕ ᰊᰰᰶ ᰍᰬ ᰚᰦᰮ ᰕᰦ ᰣᰨ ᰼ ᰣᰪᰲ ᰠᰴ ᰜ [22] ᰠᰪᰮ ᰓᰦᰯ ᰜ ᰌᰪᰭ ᰠ ᰉᰧ ᰚᰦᰵ ᰜ ᰃᰨ ᰣᰦ ᰓᰧ ᰠᰪᰮ ᰓᰦᰮ [23] ᰜ ᰌᰪᰭ ᰕ ᰜᰬᰯ ᰍᰬ ᰚᰦᰮ ᰕᰦ ᰣᰨ ᰼ ᰣᰪᰲ ᰍᰪᰰ ᰜᰤᰦᰵ ᰀᰦᰳ ᰀ ᰚᰧ [24] ᰅᰪᰵ ᰎᰴ ᰜ ᰣᰦ ᰓᰧ ᰠᰪᰮ ᰓᰦᰮ ᰜ ᰕᰶ ᰎᰫ ᰍᰬ ᰠᰪᰵ ᰕ ᰌᰪᰰ [25] ᰆᰬ ᰌᰪᰳ ᰜ ᰃᰴ ᰍ ᰌᰪᰳ ᰜ ᰕ ᰜᰬᰭ ᰓᰬ ᰠᰪᰵ ᰠᰪᰮ ᰣᰦᰮ ᰜ ᰌᰪ [26] ᰕ ᰂᰪᰮ ᰓᰦ ᰚᰦᰮ ᰕᰦ ᰣᰨ ᰼ ᰣᰪᰲ ᰍᰪᰰ ᰃᰨ ᰠ ᰇᰨ ᰜᰤᰦᰵ ᰀᰦ ᰋᰧᰭᰶ [27] ᰕ ᰚᰨ [28] ᰡᰬᰰ ᰜ ᰣᰨ ᰓᰦ ᰠ ᰕ ᰛᰩ ᰎᰴ ᰛᰬ ᰕᰪᰳ ᰙᰪ ᰛᰬ ᰉᰬᰳ ᰠᰦᰮ ᰠ ᰕᰪᰰ [29] ᰙᰪ ᰡᰪ ᰋᰨ ᰅᰪᰵ ᰠ ᰌᰩᰮ ᰜ ᰉᰧ ᰓᰦᰮ ᰎᰦ ᰚᰦᰮ ᰕᰦ ᰣᰨ ᰼ [30] ᰣᰦ ᰋᰤᰦᰭ ᰛᰬ ᰉᰧ ᰛᰬ ᰙᰩᰵ ᰉᰧ ᰓᰦᰮ ᰎᰦ ᰚᰦᰮ ᰕᰦ ᰣᰨ ᰼ ᰕᰧᰭᰶ [31] ᰕᰤᰩᰵ ᰛᰬ ᰊᰫᰵ ᰀᰫᰵ ᰙᰩᰵ ᰉᰧ ᰓᰦᰮ ᰎᰦ ᰚᰦᰮ ᰕᰦ ᰣᰨ ᰼ ᰣᰦ ᰀᰩ ᰛ [32] ᰊᰫᰵ ᰙᰩᰵ ᰉᰧ ᰓᰮᰶ ᰎᰦ ᰚᰦᰮ ᰕᰦ ᰣᰨ ᰼ ᰕᰪᰰ ᰙᰪ ᰓᰧ ᰊ ᰅᰪᰵ ᰠ [33] ᰝᰥᰤᰦᰰ ᰍᰪᰵ ᰠ ᰉᰦᰭ ᰀᰦ ᰊᰤᰬᰳ ᰕᰨ ᰜ ᰉᰦᰭ ᰀ ᰇᰧ ᰎᰦ ᰚᰦᰮ ᰕ [34] ᰣᰨ ᰼ ᰣᰨ ᰊᰤᰬᰳ ᰀᰦ ᰀ ᰌᰨ ᰠᰪ ᰠ ᰣᰦ ᰋᰧᰵᰶ ᰠ ᰣᰦ ᰉᰨ [35] ᰕᰪᰮ ᰍᰪᰰ ᰜᰧ ᰶ ᰓᰦ ᰃᰥᰪᰭ ᰕᰦᰳ ᰜᰪᰵ ᰓᰦ ᰚᰴ ᰜᰧ ᰡᰬᰰ ᰀᰦ ᰃᰨ [36] ᰓᰦ ᰠ ᰜᰨᰭ ᰀ ᰣᰫ ᰚᰨ ᰊᰬᰳ ᰀᰦ ᰊ ᰣᰤᰦ ᰓᰦ ᰠ ᰇᰨ ᰠ [37] ","annotations":[{"manifest":"m335106","canvas":"https:\/\/digitalcollections.universiteitleiden.nl\/iiif_manifest\/item:335133\/canvas\/default","mode":"line","line":"1","annotation":{"id":"https:\/\/digitalcollections.universiteitleiden.nl\/iiif_manifest\/item:335133\/canvas\/default\/annotation\/r1","type":"Annotation","motivation":"supplementing","body":{"text":"ᰣᰨ ᰼ ᰣᰬ ᰃᰨ ᰛᰨ ᰜᰪᰵ ᰅᰭᰶ ᰜ ᰕ ᰊᰰᰶ ᰍ ᰃᰴ ᰜ ᰝᰨ ᰡᰦ ᰬ ᰕᰦᰳ ᰌᰤᰦᰵ ᰟᰪᰵ","type":"TextualBody"},"target":"https:\/\/digitalcollections.universiteitleiden.nl\/iiif_manifest\/item:335133\/canvas\/default#xywh=337,222,2334,221"}},{"manifest":"m335106","canvas":"https:\/\/digitalcollections.universiteitleiden.nl\/iiif_manifest\/item:335133\/canvas\/default","mode":"line","line":"2","annotation":{"id":"https:\/\/digitalcollections.universiteitleiden.nl\/iiif_manifest\/item:335133\/canvas\/default\/annotation\/r2","type":"Annotation","motivation":"supplementing","body":{"text":"ᰃᰩ ᰚᰴ ᰑᰤᰬᰰᰳ ᰡᰬᰰ ᰜ ᰓᰦ ᰝᰪ ᰍᰪᰰ ᰜᰧ ᰓᰦ ᰊ ᰣᰤᰦ ᰊᰦᰯ ᰜ ᰠᰪᰭ ᰌᰪᰮ ᰜᰦᰵ","type":"TextualBody"},"target":"https:\/\/digitalcollections.universiteitleiden.nl\/iiif_manifest\/item:335133\/canvas\/default#xywh=319,434,2370,222"}},{"manifest":"m335106","canvas":"https:\/\/digitalcollections.universiteitleiden.nl\/iiif_manifest\/item:335133\/canvas\/default","mode":"line","line":"3","annotation":{"id":"https:\/\/digitalcollections.universiteitleiden.nl\/iiif_manifest\/item:335133\/canvas\/default\/annotation\/r3","type":"Annotation","motivation":"supplementing","body":{"text":"ᰀᰦ ᰜᰤᰦᰵ ᰣᰫᰵ ᰋᰨ ᰓᰦᰰ ᰀ ᰠᰪᰮ ᰀᰦ ᰕ ᰋᰴ ᰕ ᰉᰧᰰᰶ ᰍᰪᰵ ᰠ ᰀ ᰃᰪᰱ","type":"TextualBody"},"target":"https:\/\/digitalcollections.universiteitleiden.nl\/iiif_manifest\/item:335133\/canvas\/default#xywh=349,621,2305,245"}},{"manifest":"m335106","canvas":"https:\/\/digitalcollections.universiteitleiden.nl\/iiif_manifest\/item:335133\/canvas\/default","mode":"line","line":"4","annotation":{"id":"https:\/\/digitalcollections.universiteitleiden.nl\/iiif_manifest\/item:335133\/canvas\/default\/annotation\/r4","type":"Annotation","motivation":"supplementing","body":{"text":"ᰠ ᰕ ᰛᰪᰮ ᰣᰫᰵ ᰀᰦ ᰊᰧᰵᰶ ᰓᰧ ᰎᰦ ᰚᰦᰮ ᰕᰦ ᰣᰨ ᰼ ᰣᰬ ᰣᰨ ᰛᰬ ᰍᰪᰰ ᰙᰨ","type":"TextualBody"},"target":"https:\/\/digitalcollections.universiteitleiden.nl\/iiif_manifest\/item:335133\/canvas\/default#xywh=325,884,2314,192"}},{"manifest":"m335106","canvas":"https:\/\/digitalcollections.universiteitleiden.nl\/iiif_manifest\/item:335133\/canvas\/default","mode":"line","line":"5","annotation":{"id":"https:\/\/digitalcollections.universiteitleiden.nl\/iiif_manifest\/item:335133\/canvas\/default\/annotation\/r5","type":"Annotation","motivation":"supplementing","body":{"text":"ᰝᰥᰫᰧ ᰙᰩᰮ ᰜᰪᰵ ᰣᰫᰵ ᰜ ᰉᰩᰮ ᰍᰩᰰ ᰍᰬ ᰚᰦᰮ ᰕᰦ ᰣᰨ ᰼ ᰀᰦ ᰠᰪᰮ ᰠᰩᰳ ᰊᰪᰵ ᰠ","type":"TextualBody"},"target":"https:\/\/digitalcollections.universiteitleiden.nl\/iiif_manifest\/item:335133\/canvas\/default#xywh=358,1040,2290,237"}},{"manifest":"m335106","canvas":"https:\/\/digitalcollections.universiteitleiden.nl\/iiif_manifest\/item:335133\/canvas\/default","mode":"line","line":"6","annotation":{"id":"https:\/\/digitalcollections.universiteitleiden.nl\/iiif_manifest\/item:335133\/canvas\/default\/annotation\/r6","type":"Annotation","motivation":"supplementing","body":{"text":"ᰣᰦ ᰜᰩᰮᰶ ᰜᰤᰩᰱ ᰕᰦ ᰚᰴ ᰋᰪᰰ ᰜᰧ ᰎᰦ ᰚᰦᰮ ᰕᰦ ᰣᰨ ᰼ ᰀ ᰠᰪᰭ ᰠᰩᰳ ᰓᰦ","type":"TextualBody"},"target":"https:\/\/digitalcollections.universiteitleiden.nl\/iiif_manifest\/item:335133\/canvas\/default#xywh=349,1250,2263,201"}},{"manifest":"m335106","canvas":"https:\/\/digitalcollections.universiteitleiden.nl\/iiif_manifest\/item:335133\/canvas\/default","mode":"line","line":"7","annotation":{"id":"https:\/\/digitalcollections.universiteitleiden.nl\/iiif_manifest\/item:335133\/canvas\/default\/annotation\/r7","type":"Annotation","motivation":"supplementing","body":{"text":"ᰊᰨ ᰍᰪᰰ ᰜ ᰕ ᰚᰪᰰ ᰍᰬ ᰝᰨ ᰋᰦᰭ ᰕ ᰌᰤᰦᰯ ᰍᰪᰰ ᰣᰨ ᰚᰴ ᰜᰧ ᰎᰦ ᰚᰦᰮ","type":"TextualBody"},"target":"https:\/\/digitalcollections.universiteitleiden.nl\/iiif_manifest\/item:335133\/canvas\/default#xywh=358,1483,2248,192"}},{"manifest":"m335106","canvas":"https:\/\/digitalcollections.universiteitleiden.nl\/iiif_manifest\/item:335133\/canvas\/default","mode":"line","line":"8","annotation":{"id":"https:\/\/digitalcollections.universiteitleiden.nl\/iiif_manifest\/item:335133\/canvas\/default\/annotation\/r8","type":"Annotation","motivation":"supplementing","body":{"text":"ᰕᰦ ᰣᰨ ᰼ ᰣᰨ ᰛᰬ ᰍᰪᰰ ᰉᰨ ᰃᰧᰵᰶ ᰜᰧ ᰠ ᰌ ᰚᰴ ᰠ ᰌ ᰀᰦ ᰆᰧᰭᰶ","type":"TextualBody"},"target":"https:\/\/digitalcollections.universiteitleiden.nl\/iiif_manifest\/item:335133\/canvas\/default#xywh=363,1655,2231,224"}},{"manifest":"m335106","canvas":"https:\/\/digitalcollections.universiteitleiden.nl\/iiif_manifest\/item:335133\/canvas\/default","mode":"line","line":"9","annotation":{"id":"https:\/\/digitalcollections.universiteitleiden.nl\/iiif_manifest\/item:335133\/canvas\/default\/annotation\/r9","type":"Annotation","motivation":"supplementing","body":{"text":"ᰍᰩᰰ ᰍᰬ ᰚᰦᰮ ᰕᰦ ᰣᰨ ᰼ ᰣᰨ ᰓᰦ ᰜᰤᰦᰵ ᰀᰦ ᰋᰧ ᰡᰬᰰ ᰜ ᰎᰪᰰ ᰌᰧ ᰀᰳ","type":"TextualBody"},"target":"https:\/\/digitalcollections.universiteitleiden.nl\/iiif_manifest\/item:335133\/canvas\/default#xywh=337,1868,2207,221"}},{"manifest":"m335106","canvas":"https:\/\/digitalcollections.universiteitleiden.nl\/iiif_manifest\/item:335133\/canvas\/default","mode":"line","line":"10","annotation":{"id":"https:\/\/digitalcollections.universiteitleiden.nl\/iiif_manifest\/item:335133\/canvas\/default\/annotation\/r10","type":"Annotation","motivation":"supplementing","body":{"text":"ᰜᰧ ᰓᰦᰮ ᰉᰧ ᰎᰦ ᰚᰦᰮ ᰕᰦ ᰣᰨ ᰼ ᰝᰪᰮ ᰚᰫ ᰍᰪᰰ ᰜᰧ ᰓᰦ ᰀ ᰚᰫ ᰍ","type":"TextualBody"},"target":"https:\/\/digitalcollections.universiteitleiden.nl\/iiif_manifest\/item:335133\/canvas\/default#xywh=363,2110,2243,183"}},{"manifest":"m335106","canvas":"https:\/\/digitalcollections.universiteitleiden.nl\/iiif_manifest\/item:335133\/canvas\/default","mode":"line","line":"11","annotation":{"id":"https:\/\/digitalcollections.universiteitleiden.nl\/iiif_manifest\/item:335133\/canvas\/default\/annotation\/r11","type":"Annotation","motivation":"supplementing","body":{"text":"ᰗᰪ ᰀᰤᰬᰳ ᰕ ᰋᰩᰰ ᰍᰬ ᰚᰴ ᰜᰧ ᰜᰪᰵ ᰜᰧ ᰓᰦ ᰣᰨ ᰃᰪᰰ ᰌᰧᰵᰶ ᰍᰩᰰ ᰍᰬ","type":"TextualBody"},"target":"https:\/\/digitalcollections.universiteitleiden.nl\/iiif_manifest\/item:335133\/canvas\/default#xywh=369,2272,2184,234"}},{"manifest":"m335106","canvas":"https:\/\/digitalcollections.universiteitleiden.nl\/iiif_manifest\/item:335133\/canvas\/default","mode":"line","line":"12","annotation":{"id":"https:\/\/digitalcollections.universiteitleiden.nl\/iiif_manifest\/item:335133\/canvas\/default\/annotation\/r12","type":"Annotation","motivation":"supplementing","body":{"text":"ᰚᰴ ᰜᰧ ᰚᰦᰮ ᰕᰦ ᰣᰨ ᰼ ᰌ ᰜ ᰂᰦᰰ ᰍᰩᰰ ᰍᰬ ᰀ ᰚᰫᰭ ᰀ ᰊᰦ ᰃᰴ","type":"TextualBody"},"target":"https:\/\/digitalcollections.universiteitleiden.nl\/iiif_manifest\/item:335133\/canvas\/default#xywh=343,2497,2293,216"}},{"manifest":"m335106","canvas":"https:\/\/digitalcollections.universiteitleiden.nl\/iiif_manifest\/item:335133\/canvas\/default","mode":"line","line":"13","annotation":{"id":"https:\/\/digitalcollections.universiteitleiden.nl\/iiif_manifest\/item:335133\/canvas\/default\/annotation\/r13","type":"Annotation","motivation":"supplementing","body":{"text":"ᰎᰦᰰ ᰉᰧ ᰕᰦ ᰚᰦᰮ ᰕᰦ ᰣᰨ ᰼ ᰝᰪᰮ ᰚᰫᰭ ᰍᰪᰰ ᰣ ᰜᰧᰶ ᰓᰦ ᰜᰤᰦᰵ ᰚᰦᰮ ᰓᰨ","type":"TextualBody"},"target":"https:\/\/digitalcollections.universiteitleiden.nl\/iiif_manifest\/item:335133\/canvas\/default#xywh=331,2733,2311,181"}},{"manifest":"m335106","canvas":"https:\/\/digitalcollections.universiteitleiden.nl\/iiif_manifest\/item:335133\/canvas\/default","mode":"line","line":"14","annotation":{"id":"https:\/\/digitalcollections.universiteitleiden.nl\/iiif_manifest\/item:335133\/canvas\/default\/annotation\/r14","type":"Annotation","motivation":"supplementing","body":{"text":"ᰓᰧᰵᰶ ᰜᰤᰦᰵ ᰠ ᰓᰦ ᰜ ᰃᰪᰰ ᰍ ᰉᰩᰮ ᰍᰩᰰ ᰍᰬ ᰚᰴ ᰜᰧ ᰎᰦ ᰚᰦᰮ ᰕᰦ ᰣᰨ","type":"TextualBody"},"target":"https:\/\/digitalcollections.universiteitleiden.nl\/iiif_manifest\/item:335133\/canvas\/default#xywh=375,2931,2287,189"}},{"manifest":"m335106","canvas":"https:\/\/digitalcollections.universiteitleiden.nl\/iiif_manifest\/item:335133\/canvas\/default","mode":"line","line":"15","annotation":{"id":"https:\/\/digitalcollections.universiteitleiden.nl\/iiif_manifest\/item:335133\/canvas\/default\/annotation\/r15","type":"Annotation","motivation":"supplementing","body":{"text":"᰼ ᰕ ᰃᰫᰰ ᰕ ᰃᰤᰦᰰ ᰍᰪᰵ ᰠ ᰠ ᰌᰪᰭ ᰜ ᰀ ᰜᰪᰵ ᰕ ᰛᰩ ᰕᰦᰭ ᰌᰩᰮ ᰉᰧ","type":"TextualBody"},"target":"https:\/\/digitalcollections.universiteitleiden.nl\/iiif_manifest\/item:335133\/canvas\/default#xywh=343,3141,2263,186"}},{"manifest":"m335106","canvas":"https:\/\/digitalcollections.universiteitleiden.nl\/iiif_manifest\/item:335133\/canvas\/default","mode":"line","line":"16","annotation":{"id":"https:\/\/digitalcollections.universiteitleiden.nl\/iiif_manifest\/item:335133\/canvas\/default\/annotation\/r16","type":"Annotation","motivation":"supplementing","body":{"text":"ᰊᰪᰮ ᰣᰨ ᰚᰴ ᰜᰧ ᰎᰦ ᰚᰦᰮ ᰕᰦ ᰣᰨ ᰼ ᰙ ᰓᰦ ᰃᰴ ᰜ ᰋᰦᰮ ᰓᰨ ᰜᰧᰵᰶ","type":"TextualBody"},"target":"https:\/\/digitalcollections.universiteitleiden.nl\/iiif_manifest\/item:335133\/canvas\/default#xywh=358,3345,2272,180"}},{"manifest":"m335106","canvas":"https:\/\/digitalcollections.universiteitleiden.nl\/iiif_manifest\/item:335133\/canvas\/default","mode":"line","line":"17","annotation":{"id":"https:\/\/digitalcollections.universiteitleiden.nl\/iiif_manifest\/item:335133\/canvas\/default\/annotation\/r17","type":"Annotation","motivation":"supplementing","body":{"text":"ᰜᰤᰦᰵ ᰣᰦ ᰛᰬ ᰀᰦ ᰕ ᰛᰩ ᰣᰦ ᰀᰪᰱ ᰃᰬᰮᰭ ᰅᰪᰵ ᰎᰴ ᰛᰬ ᰌᰫ ᰌᰩᰮ ᰓᰦᰮ ᰕᰦᰯ","type":"TextualBody"},"target":"https:\/\/digitalcollections.universiteitleiden.nl\/iiif_manifest\/item:335133\/canvas\/default#xywh=358,3543,2242,186"}},{"manifest":"m335106","canvas":"https:\/\/digitalcollections.universiteitleiden.nl\/iiif_manifest\/item:335133\/canvas\/default","mode":"line","line":"18","annotation":{"id":"https:\/\/digitalcollections.universiteitleiden.nl\/iiif_manifest\/item:335133\/canvas\/default\/annotation\/r18","type":"Annotation","motivation":"supplementing","body":{"text":"ᰀᰦ ᰊᰪᰮ ᰣᰨ ᰚᰴ ᰜᰧ ᰊᰤᰬᰰ ᰀᰦ ᰀ ᰠᰪ ᰠ ᰣᰦ ᰆᰧᰵᰶ ᰉᰪᰮ ᰍᰪᰰ ᰜᰧᰴ","type":"TextualBody"},"target":"https:\/\/digitalcollections.universiteitleiden.nl\/iiif_manifest\/item:335133\/canvas\/default#xywh=396,3750,2281,230"}},{"manifest":"m335106","canvas":"https:\/\/digitalcollections.universiteitleiden.nl\/iiif_manifest\/item:335133\/canvas\/default","mode":"line","line":"19","annotation":{"id":"https:\/\/digitalcollections.universiteitleiden.nl\/iiif_manifest\/item:335133\/canvas\/default\/annotation\/r19","type":"Annotation","motivation":"supplementing","body":{"text":"ᰓᰦ ᰣᰦ ᰜᰴ ᰃᰪᰮᰶ ᰃᰩᰮᰶ ᰕᰦᰳ ᰍᰦ ᰚᰴ ᰜᰧ ᰢᰪᰵ ᰠ ᰃᰨ ᰠ ᰜᰤᰨᰵ ᰀ ᰀᰪ","type":"TextualBody"},"target":"https:\/\/digitalcollections.universiteitleiden.nl\/iiif_manifest\/item:335133\/canvas\/default#xywh=2902,216,2272,221"}},{"manifest":"m335106","canvas":"https:\/\/digitalcollections.universiteitleiden.nl\/iiif_manifest\/item:335133\/canvas\/default","mode":"line","line":"20","annotation":{"id":"https:\/\/digitalcollections.universiteitleiden.nl\/iiif_manifest\/item:335133\/canvas\/default\/annotation\/r20","type":"Annotation","motivation":"supplementing","body":{"text":"ᰚᰴ ᰕ ᰉᰧᰰᰶ ᰍᰪᰵ ᰠ ᰀᰦ ᰀᰦ ᰍᰬ ᰌᰦᰮ ᰚᰴ ᰠ ᰜᰤᰦᰵ ᰀᰦ ᰋᰧᰰᰶ ᰓᰦ","type":"TextualBody"},"target":"https:\/\/digitalcollections.universiteitleiden.nl\/iiif_manifest\/item:335133\/canvas\/default#xywh=2896,434,2275,216"}},{"manifest":"m335106","canvas":"https:\/\/digitalcollections.universiteitleiden.nl\/iiif_manifest\/item:335133\/canvas\/default","mode":"line","line":"21","annotation":{"id":"https:\/\/digitalcollections.universiteitleiden.nl\/iiif_manifest\/item:335133\/canvas\/default\/annotation\/r21","type":"Annotation","motivation":"supplementing","body":{"text":"ᰣᰨ ᰓᰦ ᰠ ᰕ ᰛᰩ ᰌᰨ ᰙᰩᰵ ᰙ ᰌᰤᰪ ᰜᰪᰵ ᰠᰩᰳ ᰓᰪᰭ ᰜᰪᰵ ᰣᰦ ᰕᰬᰰ ᰣᰦ ᰆᰧᰰᰶ","type":"TextualBody"},"target":"https:\/\/digitalcollections.universiteitleiden.nl\/iiif_manifest\/item:335133\/canvas\/default#xywh=2878,635,2290,225"}},{"manifest":"m335106","canvas":"https:\/\/digitalcollections.universiteitleiden.nl\/iiif_manifest\/item:335133\/canvas\/default","mode":"line","line":"22","annotation":{"id":"https:\/\/digitalcollections.universiteitleiden.nl\/iiif_manifest\/item:335133\/canvas\/default\/annotation\/r22","type":"Annotation","motivation":"supplementing","body":{"text":"ᰋᰴ ᰓᰦᰮ ᰣᰦ ᰃᰨ ᰅᰭᰶ ᰜ ᰕ ᰊᰰᰶ ᰍᰬ ᰚᰦᰮ ᰕᰦ ᰣᰨ ᰼ ᰣᰪᰲ ᰠᰴ ᰜ","type":"TextualBody"},"target":"https:\/\/digitalcollections.universiteitleiden.nl\/iiif_manifest\/item:335133\/canvas\/default#xywh=2887,854,2296,222"}},{"manifest":"m335106","canvas":"https:\/\/digitalcollections.universiteitleiden.nl\/iiif_manifest\/item:335133\/canvas\/default","mode":"line","line":"23","annotation":{"id":"https:\/\/digitalcollections.universiteitleiden.nl\/iiif_manifest\/item:335133\/canvas\/default\/annotation\/r23","type":"Annotation","motivation":"supplementing","body":{"text":"ᰠᰪᰮ ᰓᰦᰯ ᰜ ᰌᰪᰭ ᰠ ᰉᰧ ᰚᰦᰵ ᰜ ᰃᰨ ᰣᰦ ᰓᰧ ᰠᰪᰮ ᰓᰦᰮ","type":"TextualBody"},"target":"https:\/\/digitalcollections.universiteitleiden.nl\/iiif_manifest\/item:335133\/canvas\/default#xywh=2931,1055,2237,201"}},{"manifest":"m335106","canvas":"https:\/\/digitalcollections.universiteitleiden.nl\/iiif_manifest\/item:335133\/canvas\/default","mode":"line","line":"24","annotation":{"id":"https:\/\/digitalcollections.universiteitleiden.nl\/iiif_manifest\/item:335133\/canvas\/default\/annotation\/r24","type":"Annotation","motivation":"supplementing","body":{"text":"ᰜ ᰌᰪᰭ ᰕ ᰜᰬᰯ ᰍᰬ ᰚᰦᰮ ᰕᰦ ᰣᰨ ᰼ ᰣᰪᰲ ᰍᰪᰰ ᰜᰤᰦᰵ ᰀᰦᰳ ᰀ ᰚᰧ","type":"TextualBody"},"target":"https:\/\/digitalcollections.universiteitleiden.nl\/iiif_manifest\/item:335133\/canvas\/default#xywh=2925,1232,2187,240"}},{"manifest":"m335106","canvas":"https:\/\/digitalcollections.universiteitleiden.nl\/iiif_manifest\/item:335133\/canvas\/default","mode":"line","line":"25","annotation":{"id":"https:\/\/digitalcollections.universiteitleiden.nl\/iiif_manifest\/item:335133\/canvas\/default\/annotation\/r25","type":"Annotation","motivation":"supplementing","body":{"text":"ᰅᰪᰵ ᰎᰴ ᰜ ᰣᰦ ᰓᰧ ᰠᰪᰮ ᰓᰦᰮ ᰜ ᰕᰶ ᰎᰫ ᰍᰬ ᰠᰪᰵ ᰕ ᰌᰪᰰ","type":"TextualBody"},"target":"https:\/\/digitalcollections.universiteitleiden.nl\/iiif_manifest\/item:335133\/canvas\/default#xywh=2914,1445,2216,228"}},{"manifest":"m335106","canvas":"https:\/\/digitalcollections.universiteitleiden.nl\/iiif_manifest\/item:335133\/canvas\/default","mode":"line","line":"26","annotation":{"id":"https:\/\/digitalcollections.universiteitleiden.nl\/iiif_manifest\/item:335133\/canvas\/default\/annotation\/r26","type":"Annotation","motivation":"supplementing","body":{"text":"ᰆᰬ ᰌᰪᰳ ᰜ ᰃᰴ ᰍ ᰌᰪᰳ ᰜ ᰕ ᰜᰬᰭ ᰓᰬ ᰠᰪᰵ ᰠᰪᰮ ᰣᰦᰮ ᰜ ᰌᰪ","type":"TextualBody"},"target":"https:\/\/digitalcollections.universiteitleiden.nl\/iiif_manifest\/item:335133\/canvas\/default#xywh=2928,1667,2249,215"}},{"manifest":"m335106","canvas":"https:\/\/digitalcollections.universiteitleiden.nl\/iiif_manifest\/item:335133\/canvas\/default","mode":"line","line":"27","annotation":{"id":"https:\/\/digitalcollections.universiteitleiden.nl\/iiif_manifest\/item:335133\/canvas\/default\/annotation\/r27","type":"Annotation","motivation":"supplementing","body":{"text":"ᰕ ᰂᰪᰮ ᰓᰦ ᰚᰦᰮ ᰕᰦ ᰣᰨ ᰼ ᰣᰪᰲ ᰍᰪᰰ ᰃᰨ ᰠ ᰇᰨ ᰜᰤᰦᰵ ᰀᰦ ᰋᰧᰭᰶ","type":"TextualBody"},"target":"https:\/\/digitalcollections.universiteitleiden.nl\/iiif_manifest\/item:335133\/canvas\/default#xywh=2955,1835,2172,251"}},{"manifest":"m335106","canvas":"https:\/\/digitalcollections.universiteitleiden.nl\/iiif_manifest\/item:335133\/canvas\/default","mode":"line","line":"28","annotation":{"id":"https:\/\/digitalcollections.universiteitleiden.nl\/iiif_manifest\/item:335133\/canvas\/default\/annotation\/r28","type":"Annotation","motivation":"supplementing","body":{"text":"ᰕ ᰚᰨ","type":"TextualBody"},"target":"https:\/\/digitalcollections.universiteitleiden.nl\/iiif_manifest\/item:335133\/canvas\/default#xywh=4406,2006,186,139"}},{"manifest":"m335106","canvas":"https:\/\/digitalcollections.universiteitleiden.nl\/iiif_manifest\/item:335133\/canvas\/default","mode":"line","line":"29","annotation":{"id":"https:\/\/digitalcollections.universiteitleiden.nl\/iiif_manifest\/item:335133\/canvas\/default\/annotation\/r29","type":"Annotation","motivation":"supplementing","body":{"text":"ᰡᰬᰰ ᰜ ᰣᰨ ᰓᰦ ᰠ ᰕ ᰛᰩ ᰎᰴ ᰛᰬ ᰕᰪᰳ ᰙᰪ ᰛᰬ ᰉᰬᰳ ᰠᰦᰮ ᰠ ᰕᰪᰰ","type":"TextualBody"},"target":"https:\/\/digitalcollections.universiteitleiden.nl\/iiif_manifest\/item:335133\/canvas\/default#xywh=2937,2080,2187,237"}},{"manifest":"m335106","canvas":"https:\/\/digitalcollections.universiteitleiden.nl\/iiif_manifest\/item:335133\/canvas\/default","mode":"line","line":"30","annotation":{"id":"https:\/\/digitalcollections.universiteitleiden.nl\/iiif_manifest\/item:335133\/canvas\/default\/annotation\/r30","type":"Annotation","motivation":"supplementing","body":{"text":"ᰙᰪ ᰡᰪ ᰋᰨ ᰅᰪᰵ ᰠ ᰌᰩᰮ ᰜ ᰉᰧ ᰓᰦᰮ ᰎᰦ ᰚᰦᰮ ᰕᰦ ᰣᰨ ᰼","type":"TextualBody"},"target":"https:\/\/digitalcollections.universiteitleiden.nl\/iiif_manifest\/item:335133\/canvas\/default#xywh=2973,2258,2166,310"}},{"manifest":"m335106","canvas":"https:\/\/digitalcollections.universiteitleiden.nl\/iiif_manifest\/item:335133\/canvas\/default","mode":"line","line":"31","annotation":{"id":"https:\/\/digitalcollections.universiteitleiden.nl\/iiif_manifest\/item:335133\/canvas\/default\/annotation\/r31","type":"Annotation","motivation":"supplementing","body":{"text":"ᰣᰦ ᰋᰤᰦᰭ ᰛᰬ ᰉᰧ ᰛᰬ ᰙᰩᰵ ᰉᰧ ᰓᰦᰮ ᰎᰦ ᰚᰦᰮ ᰕᰦ ᰣᰨ ᰼ ᰕᰧᰭᰶ","type":"TextualBody"},"target":"https:\/\/digitalcollections.universiteitleiden.nl\/iiif_manifest\/item:335133\/canvas\/default#xywh=2914,2459,2219,227"}},{"manifest":"m335106","canvas":"https:\/\/digitalcollections.universiteitleiden.nl\/iiif_manifest\/item:335133\/canvas\/default","mode":"line","line":"32","annotation":{"id":"https:\/\/digitalcollections.universiteitleiden.nl\/iiif_manifest\/item:335133\/canvas\/default\/annotation\/r32","type":"Annotation","motivation":"supplementing","body":{"text":"ᰕᰤᰩᰵ ᰛᰬ ᰊᰫᰵ ᰀᰫᰵ ᰙᰩᰵ ᰉᰧ ᰓᰦᰮ ᰎᰦ ᰚᰦᰮ ᰕᰦ ᰣᰨ ᰼ ᰣᰦ ᰀᰩ ᰛ","type":"TextualBody"},"target":"https:\/\/digitalcollections.universiteitleiden.nl\/iiif_manifest\/item:335133\/canvas\/default#xywh=2922,2701,2208,242"}},{"manifest":"m335106","canvas":"https:\/\/digitalcollections.universiteitleiden.nl\/iiif_manifest\/item:335133\/canvas\/default","mode":"line","line":"33","annotation":{"id":"https:\/\/digitalcollections.universiteitleiden.nl\/iiif_manifest\/item:335133\/canvas\/default\/annotation\/r33","type":"Annotation","motivation":"supplementing","body":{"text":"ᰊᰫᰵ ᰙᰩᰵ ᰉᰧ ᰓᰮᰶ ᰎᰦ ᰚᰦᰮ ᰕᰦ ᰣᰨ ᰼ ᰕᰪᰰ ᰙᰪ ᰓᰧ ᰊ ᰅᰪᰵ ᰠ","type":"TextualBody"},"target":"https:\/\/digitalcollections.universiteitleiden.nl\/iiif_manifest\/item:335133\/canvas\/default#xywh=2931,2899,2217,195"}},{"manifest":"m335106","canvas":"https:\/\/digitalcollections.universiteitleiden.nl\/iiif_manifest\/item:335133\/canvas\/default","mode":"line","line":"34","annotation":{"id":"https:\/\/digitalcollections.universiteitleiden.nl\/iiif_manifest\/item:335133\/canvas\/default\/annotation\/r34","type":"Annotation","motivation":"supplementing","body":{"text":"ᰝᰥᰤᰦᰰ ᰍᰪᰵ ᰠ ᰉᰦᰭ ᰀᰦ ᰊᰤᰬᰳ ᰕᰨ ᰜ ᰉᰦᰭ ᰀ ᰇᰧ ᰎᰦ ᰚᰦᰮ ᰕ","type":"TextualBody"},"target":"https:\/\/digitalcollections.universiteitleiden.nl\/iiif_manifest\/item:335133\/canvas\/default#xywh=2996,3091,2158,204"}},{"manifest":"m335106","canvas":"https:\/\/digitalcollections.universiteitleiden.nl\/iiif_manifest\/item:335133\/canvas\/default","mode":"line","line":"35","annotation":{"id":"https:\/\/digitalcollections.universiteitleiden.nl\/iiif_manifest\/item:335133\/canvas\/default\/annotation\/r35","type":"Annotation","motivation":"supplementing","body":{"text":"ᰣᰨ ᰼ ᰣᰨ ᰊᰤᰬᰳ ᰀᰦ ᰀ ᰌᰨ ᰠᰪ ᰠ ᰣᰦ ᰋᰧᰵᰶ ᰠ ᰣᰦ ᰉᰨ","type":"TextualBody"},"target":"https:\/\/digitalcollections.universiteitleiden.nl\/iiif_manifest\/item:335133\/canvas\/default#xywh=2952,3316,2157,203"}},{"manifest":"m335106","canvas":"https:\/\/digitalcollections.universiteitleiden.nl\/iiif_manifest\/item:335133\/canvas\/default","mode":"line","line":"36","annotation":{"id":"https:\/\/digitalcollections.universiteitleiden.nl\/iiif_manifest\/item:335133\/canvas\/default\/annotation\/r36","type":"Annotation","motivation":"supplementing","body":{"text":"ᰕᰪᰮ ᰍᰪᰰ ᰜᰧ ᰶ ᰓᰦ ᰃᰥᰪᰭ ᰕᰦᰳ ᰜᰪᰵ ᰓᰦ ᰚᰴ ᰜᰧ ᰡᰬᰰ ᰀᰦ ᰃᰨ","type":"TextualBody"},"target":"https:\/\/digitalcollections.universiteitleiden.nl\/iiif_manifest\/item:335133\/canvas\/default#xywh=2990,3493,2131,227"}},{"manifest":"m335106","canvas":"https:\/\/digitalcollections.universiteitleiden.nl\/iiif_manifest\/item:335133\/canvas\/default","mode":"line","line":"37","annotation":{"id":"https:\/\/digitalcollections.universiteitleiden.nl\/iiif_manifest\/item:335133\/canvas\/default\/annotation\/r37","type":"Annotation","motivation":"supplementing","body":{"text":"ᰓᰦ ᰠ ᰜᰨᰭ ᰀ ᰣᰫ ᰚᰨ ᰊᰬᰳ ᰀᰦ ᰊ ᰣᰤᰦ ᰓᰦ ᰠ ᰇᰨ ᰠ","type":"TextualBody"},"target":"https:\/\/digitalcollections.universiteitleiden.nl\/iiif_manifest\/item:335133\/canvas\/default#xywh=3026,3703,2086,242"}}]}