{"manifest":"m335106","canvas":"https:\/\/digitalcollections.universiteitleiden.nl\/iiif_manifest\/item:335111\/canvas\/default","page":"ᰉᰧ ᰣᰦ ᰃᰨ ᰛᰬ ᰎᰪᰰ ᰠᰦᰭ ᰕ ᰉᰧᰰ ᰡᰬ ᰚᰴ ᰠᰦᰭ ᰆᰧᰵᰶ ᰅᰪᰵ ᰠ ᰣᰦ ᰜᰩᰮ [1] ᰃᰪᰮ ᰚᰴ ᰜᰧ ᰓᰧ ᰎᰦ ᰚᰦᰮ ᰕᰦ ᰣᰨ ᰼ ᰣᰪᰲ ᰠ ᰠ ᰃᰥᰦᰳ ᰀᰦ ᰊᰪᰵ ᰃᰪᰳ ᰠ [2] ᰝᰥᰤᰦᰰ ᰋᰤᰦᰵ ᰜᰵ ᰝᰤᰩᰱ ᰗᰦᰮ ᰓᰪ ᰅᰦᰰ ᰉᰧ ᰅᰪᰵ ᰠ ᰀᰤᰵ ᰀ ᰀᰤᰬᰳ ᰉᰧ ᰎᰦ [3] ᰚᰦᰮ ᰕᰦ ᰣᰨ ᰼ ᰣᰪᰲ ᰛᰬᰰ ᰆᰪᰮ ᰜ ᰎᰭᰶ ᰍᰨ ᰡᰬᰰ ᰜ ᰕ ᰛᰩ ᰀᰦᰳ ᰛᰤᰬᰮ ᰣᰦ ᰓᰴ [4] ᰊᰪᰭ ᰊᰩᰮ ᰜᰩᰮ ᰎᰴ ᰃᰪᰰ ᰍ ᰜᰦᰵ ᰓᰪ ᰜᰵ ᰊᰧᰮᰶ ᰜᰪᰵ ᰊ ᰃᰥᰫᰮ ᰀᰦ ᰕᰦᰯ [5] ᰌᰦ ᰉᰧ ᰎᰦ ᰚᰦᰮ ᰕᰦ ᰣᰨ ᰼ ᰣᰬ ᰣᰦ ᰛᰬ ᰠᰴ ᰛᰬ ᰡᰫ ᰕᰦᰳ ᰊᰪᰵ ᰃᰩ ᰚᰴ [6] ᰟᰤᰬᰳ ᰡᰬᰰ ᰜ ᰣᰦ ᰋᰧᰵᰶ ᰉᰪᰮ ᰍᰪᰰ ᰜᰧ ᰓᰦ ᰕ ᰛᰩ ᰣᰦ ᰛᰬ ᰠᰩᰵ ᰛᰬ ᰠ ᰣᰤᰦ [7] ᰓᰦ ᰊᰦᰮᰯ ᰜ ᰠᰪᰭ ᰌᰪᰮ ᰜᰤᰦᰵ ᰀᰦ ᰓᰦᰮ ᰓᰦ ᰑᰨ ᰀᰪᰱ ᰗᰦᰮ ᰜᰪᰵ ᰙᰫ ᰓᰦ ᰋᰦᰮ [8] ᰓᰧᰭᰶ ᰋᰦᰮ ᰆᰩᰵᰶ ᰊᰪᰭ ᰉᰩᰮ ᰗᰦᰮ ᰠᰩᰳ ᰜᰪᰵ ᰓᰧ ᰋᰨ ᰅᰪᰵ ᰠ ᰇᰧᰶ ᰀᰪᰱ ᰀᰤᰩᰳ [9] ᰆᰫ ᰜᰪᰵ ᰋᰦᰮ ᰓᰧᰶ ᰗᰦᰮ ᰜᰪᰵ ᰓᰧ ᰋᰨ ᰢᰪᰵ ᰠ ᰜ ᰚᰨ ᰜ ᰠᰩᰵ ᰠ [10] ᰣᰦ ᰜᰨᰮ ᰃᰪᰮ ᰚᰴ ᰜᰧ ᰓᰧ ᰎᰦ ᰚᰦᰮ ᰕᰦ ᰣᰨ ᰼ ᰣᰪᰲ ᰛᰬᰰ ᰕᰧ ᰜ ᰙᰩᰵ ᰜᰪᰵ [11] ᰎᰰᰶ ᰡᰬᰰ ᰜ ᰜᰤᰦᰵ ᰎᰪ ᰊᰦᰮ ᰊᰧᰮᰶ ᰕᰨ ᰀᰦᰳ ᰀᰦ ᰋᰧᰶ ᰜᰪᰵ ᰎᰰᰶ ᰡᰬᰰ ᰜ [12] ᰊ ᰜᰤᰦᰵ ᰍᰪᰰ ᰎᰪᰰ ᰇᰨ ᰠ ᰜᰴ ᰌᰤᰩᰮ ᰀᰦᰳ ᰊ ᰋᰧᰭᰶ ᰜᰪᰵ ᰟᰨ ᰜᰪᰵ ᰋᰧᰶ [13] ᰢᰪᰵ ᰠ ᰠ ᰃᰥᰦᰱ ᰀᰦ ᰎᰪᰰ ᰈᰨ ᰜᰦᰮ ᰋᰨ ᰅᰪᰵ ᰠ ᰣᰦ ᰀᰴ ᰀᰦ ᰕ ᰛᰩ [14] ᰃᰤᰦᰮ ᰣᰨ ᰚᰨ ᰜᰪᰵ ᰕᰪᰰ ᰈᰨ ᰠ ᰣᰦ ᰀᰤᰩᰰ ᰛᰤᰬᰯ ᰜ ᰜᰳᰶ ᰜᰪᰵ ᰃᰤᰩᰳ ᰉᰩᰰ ᰍᰪᰵ [15] ᰕ ᰛᰩ ᰛᰬᰯ ᰜ ᰛᰬᰯ ᰜ ᰙᰩᰭ ᰜᰪᰵ ᰕᰦᰭ ᰍᰩᰰ ᰍᰬ ᰚᰦᰮ ᰕᰦ ᰣᰨ ᰼ ᰀ ᰋᰧᰭᰶ ᰛᰬ [16] ᰜ ᰀᰦ ᰎᰪᰰ ᰥᰨ ᰎᰪᰰ ᰜᰧ ᰝᰤᰬᰰ ᰕᰨ ᰊᰫᰮ ᰋᰨ ᰅᰪᰵ ᰠ ᰕ ᰛᰩ ᰀᰦᰳ [17] ᰛᰤᰬᰮ ᰗᰦᰮ ᰊᰧᰮᰶ ᰅᰪᰵ ᰠ ᰗᰩᰳᰶ ᰡᰪᰵ ᰠ ᰓᰦ ᰌᰨ ᰊᰦᰮ ᰊ ᰕᰦ ᰍᰩᰰ ᰍᰬ [18] ᰚᰦᰮ ᰕᰦ ᰣᰨ ᰼ ᰀᰪᰲ ᰠᰩᰵ ᰛᰬ ᰈᰪᰮ ᰙᰩᰵ ᰕᰦᰳ ᰜᰪᰵ ᰕ ᰛᰩ ᰟᰨ ᰣᰧᰳᰶ ᰊᰪᰵ ᰠ [19] ᰜᰬᰰ ᰀᰪᰮ ᰓᰪ ᰊ ᰜᰪᰵ ᰕᰦ ᰜᰪᰵ ᰠᰩᰳ ᰊᰪᰵ ᰠ ᰣᰦ ᰜᰩᰮ ᰃᰪᰮ ᰚᰴ ᰌᰪᰰ [20] ᰓᰧ ᰎᰦ ᰚᰦᰮ ᰕᰦ ᰣᰨ ᰼ ᰣᰨ ᰛᰬ ᰍᰪᰰ ᰀᰤᰴ ᰀᰦᰳ ᰀᰦ ᰛᰦᰯ ᰛ ᰓ ᰶ ᰀ ᰛᰪᰮ ᰚᰴ [21] ᰠ ᰚᰫᰭ ᰕᰪᰰ ᰆᰧ ᰶ ᰛᰫ ᰚᰴ ᰜ ᰣᰨ ᰓᰦ ᰓᰦᰮ ᰉᰧ ᰎᰦ ᰚᰦᰮ ᰕᰦ ᰣᰨ ᰼ [22] ᰚᰴ ᰋᰦᰯ ᰜ ᰜᰩᰳ ᰓᰨ ᰉᰧ ᰜ ᰃᰴ ᰍ ᰛᰧᰵᰶ ᰀᰦᰮ ᰌᰪᰰ ᰓᰧ ᰓᰨ ᰣᰨ ᰀ ᰚᰫ [23] ᰎᰴ ᰍ ᰜᰤᰦᰵ ᰣᰦ ᰓᰦ ᰍᰪᰰ ᰜᰩᰳ ᰜᰪᰵ ᰕ ᰋᰩᰰ ᰍᰬ ᰚᰴ ᰜᰧ ᰓᰦᰮ ᰎᰦ ᰚᰦᰮ [24] ᰕᰦ ᰣᰨ ᰼ ᰣᰬ ᰃᰨ ᰍᰪᰰ ᰟᰤᰬᰰ ᰓᰦ ᰣᰦ ᰛᰬ ᰠᰩᰵ ᰊᰦᰯ ᰜ ᰓᰦᰮ ᰓᰦ ᰡᰫ ᰕᰳ [25] ᰊᰪᰵ ᰃᰨ ᰚᰴ ᰣᰤᰬᰳ ᰃᰬᰯ ᰜ ᰀ ᰌᰨ ᰠᰪ ᰋᰧᰵᰶ ᰌᰪᰮ ᰍᰪᰰ ᰜᰧ ᰓᰦ ᰊ ᰣᰤᰦ [26] ᰊᰦᰯ ᰜ ᰓᰦᰮ ᰓᰦ ᰊ ᰌᰨ ᰠ ᰜᰤᰦᰵ ᰀᰦ ᰓᰦᰮ ᰉᰧ ᰠ ᰋᰭ ᰀᰦ ᰕ ᰛᰩ ᰀᰦ [27] ᰀᰤᰬᰰ ᰋᰦᰭ ᰜᰪᰵ ᰎ ᰍᰨ ᰎᰪᰰ ᰌᰧ ᰠ ᰌᰤᰪ ᰜᰪᰵ ᰕᰧ ᰶ ᰠ ᰗᰦᰵ ᰀᰩ ᰃᰪᰰ [28] ᰍ ᰌᰦᰯ ᰜᰪᰵ ᰕᰦᰭ ᰀᰩᰰ ᰍᰪᰵ ᰠ ᰜ ᰚᰨ ᰜ ᰠᰩᰵ ᰜᰩᰳ ᰜᰪᰵ ᰙᰩᰰ ᰓᰦᰮ ᰕᰦ [29] ᰚᰴ ᰌᰪᰮ ᰓᰧ ᰎᰦ ᰚᰦᰮ ᰕᰦ ᰣᰨ ᰼ ᰣᰨ ᰊᰤᰬᰳ ᰀᰦ ᰠ ᰜᰤᰨ ᰚᰴ ᰜ ᰕ ᰚᰪᰰ ᰍ [30] ᰠ ᰣᰦ ᰀᰦ ᰓᰥᰦᰵ ᰕᰦ ᰀᰪ ᰠ ᰌ ᰀᰦ ᰋᰧᰰᰶ ᰍᰩᰰ ᰍᰬ ᰚᰦᰮ ᰕᰦ ᰣᰨ ᰼ [31] ᰣᰨ ᰓᰦ ᰠ ᰕ ᰛᰩ ᰛᰬ ᰊᰪᰭ ᰊᰨᰮ ᰎᰩᰰ ᰓᰦᰮ ᰅᰪᰵ ᰠ ᰀᰪᰲ ᰃᰪ ᰠ ᰊᰪᰭ [32] ᰎᰪᰵ ᰀᰦ ᰣᰦ ᰕᰧᰭᰶ ᰉᰧ ᰓᰦᰮ ᰎᰦ ᰚᰦᰮ ᰕᰦ ᰣᰨ ᰼ ᰝᰪᰮ ᰚᰫ ᰠ ᰆᰧᰭᰶ [33] ᰠᰴ ᰎᰬ ᰜᰩᰮ ᰀᰩᰰ ᰍᰪᰰ ᰕ ᰛᰩ ᰛᰬ ᰎᰳᰶ ᰀᰪᰱ ᰠ ᰎᰬ ᰎᰫ ᰀᰪᰱ ᰠ ᰓᰫᰮ [34] ᰀᰩᰮ ᰍᰪᰰ ᰃᰨ ᰛᰫᰵ ᰀᰪᰱ ᰠ ᰣᰦ ᰃᰤᰦᰱ ᰕᰨ ᰀ ᰋᰧᰭᰶ ᰀᰦ ᰃᰤᰩᰮ ᰋᰨ ᰜᰪᰵ [35] ᰀᰩᰵ ᰊᰤᰫᰮ ᰋᰨ ᰛᰬ ᰙᰩᰵ ᰣᰦ ᰀ ᰀᰦ ᰗᰦᰮ ᰜᰴ ᰜᰪᰵ ᰓᰦᰮ ᰉᰧ ᰎᰦ ᰚᰦᰮ ᰕ [36] ","annotations":[{"manifest":"m335106","canvas":"https:\/\/digitalcollections.universiteitleiden.nl\/iiif_manifest\/item:335111\/canvas\/default","mode":"line","line":"1","annotation":{"id":"https:\/\/digitalcollections.universiteitleiden.nl\/iiif_manifest\/item:335111\/canvas\/default\/annotation\/r1","type":"Annotation","motivation":"supplementing","body":{"text":"ᰉᰧ ᰣᰦ ᰃᰨ ᰛᰬ ᰎᰪᰰ ᰠᰦᰭ ᰕ ᰉᰧᰰ ᰡᰬ ᰚᰴ ᰠᰦᰭ ᰆᰧᰵᰶ ᰅᰪᰵ ᰠ ᰣᰦ ᰜᰩᰮ","type":"TextualBody"},"target":"https:\/\/digitalcollections.universiteitleiden.nl\/iiif_manifest\/item:335111\/canvas\/default#xywh=312,289,2267,163"}},{"manifest":"m335106","canvas":"https:\/\/digitalcollections.universiteitleiden.nl\/iiif_manifest\/item:335111\/canvas\/default","mode":"line","line":"2","annotation":{"id":"https:\/\/digitalcollections.universiteitleiden.nl\/iiif_manifest\/item:335111\/canvas\/default\/annotation\/r2","type":"Annotation","motivation":"supplementing","body":{"text":"ᰃᰪᰮ ᰚᰴ ᰜᰧ ᰓᰧ ᰎᰦ ᰚᰦᰮ ᰕᰦ ᰣᰨ ᰼ ᰣᰪᰲ ᰠ ᰠ ᰃᰥᰦᰳ ᰀᰦ ᰊᰪᰵ ᰃᰪᰳ ᰠ","type":"TextualBody"},"target":"https:\/\/digitalcollections.universiteitleiden.nl\/iiif_manifest\/item:335111\/canvas\/default#xywh=298,487,2316,199"}},{"manifest":"m335106","canvas":"https:\/\/digitalcollections.universiteitleiden.nl\/iiif_manifest\/item:335111\/canvas\/default","mode":"line","line":"3","annotation":{"id":"https:\/\/digitalcollections.universiteitleiden.nl\/iiif_manifest\/item:335111\/canvas\/default\/annotation\/r3","type":"Annotation","motivation":"supplementing","body":{"text":"ᰝᰥᰤᰦᰰ ᰋᰤᰦᰵ ᰜᰵ ᰝᰤᰩᰱ ᰗᰦᰮ ᰓᰪ ᰅᰦᰰ ᰉᰧ ᰅᰪᰵ ᰠ ᰀᰤᰵ ᰀ ᰀᰤᰬᰳ ᰉᰧ ᰎᰦ","type":"TextualBody"},"target":"https:\/\/digitalcollections.universiteitleiden.nl\/iiif_manifest\/item:335111\/canvas\/default#xywh=347,674,2264,216"}},{"manifest":"m335106","canvas":"https:\/\/digitalcollections.universiteitleiden.nl\/iiif_manifest\/item:335111\/canvas\/default","mode":"line","line":"4","annotation":{"id":"https:\/\/digitalcollections.universiteitleiden.nl\/iiif_manifest\/item:335111\/canvas\/default\/annotation\/r4","type":"Annotation","motivation":"supplementing","body":{"text":"ᰚᰦᰮ ᰕᰦ ᰣᰨ ᰼ ᰣᰪᰲ ᰛᰬᰰ ᰆᰪᰮ ᰜ ᰎᰭᰶ ᰍᰨ ᰡᰬᰰ ᰜ ᰕ ᰛᰩ ᰀᰦᰳ ᰛᰤᰬᰮ ᰣᰦ ᰓᰴ","type":"TextualBody"},"target":"https:\/\/digitalcollections.universiteitleiden.nl\/iiif_manifest\/item:335111\/canvas\/default#xywh=330,910,2278,199"}},{"manifest":"m335106","canvas":"https:\/\/digitalcollections.universiteitleiden.nl\/iiif_manifest\/item:335111\/canvas\/default","mode":"line","line":"5","annotation":{"id":"https:\/\/digitalcollections.universiteitleiden.nl\/iiif_manifest\/item:335111\/canvas\/default\/annotation\/r5","type":"Annotation","motivation":"supplementing","body":{"text":"ᰊᰪᰭ ᰊᰩᰮ ᰜᰩᰮ ᰎᰴ ᰃᰪᰰ ᰍ ᰜᰦᰵ ᰓᰪ ᰜᰵ ᰊᰧᰮᰶ ᰜᰪᰵ ᰊ ᰃᰥᰫᰮ ᰀᰦ ᰕᰦᰯ","type":"TextualBody"},"target":"https:\/\/digitalcollections.universiteitleiden.nl\/iiif_manifest\/item:335111\/canvas\/default#xywh=330,1065,2281,306"}},{"manifest":"m335106","canvas":"https:\/\/digitalcollections.universiteitleiden.nl\/iiif_manifest\/item:335111\/canvas\/default","mode":"line","line":"6","annotation":{"id":"https:\/\/digitalcollections.universiteitleiden.nl\/iiif_manifest\/item:335111\/canvas\/default\/annotation\/r6","type":"Annotation","motivation":"supplementing","body":{"text":"ᰌᰦ ᰉᰧ ᰎᰦ ᰚᰦᰮ ᰕᰦ ᰣᰨ ᰼ ᰣᰬ ᰣᰦ ᰛᰬ ᰠᰴ ᰛᰬ ᰡᰫ ᰕᰦᰳ ᰊᰪᰵ ᰃᰩ ᰚᰴ","type":"TextualBody"},"target":"https:\/\/digitalcollections.universiteitleiden.nl\/iiif_manifest\/item:335111\/canvas\/default#xywh=356,1322,2305,189"}},{"manifest":"m335106","canvas":"https:\/\/digitalcollections.universiteitleiden.nl\/iiif_manifest\/item:335111\/canvas\/default","mode":"line","line":"7","annotation":{"id":"https:\/\/digitalcollections.universiteitleiden.nl\/iiif_manifest\/item:335111\/canvas\/default\/annotation\/r7","type":"Annotation","motivation":"supplementing","body":{"text":"ᰟᰤᰬᰳ ᰡᰬᰰ ᰜ ᰣᰦ ᰋᰧᰵᰶ ᰉᰪᰮ ᰍᰪᰰ ᰜᰧ ᰓᰦ ᰕ ᰛᰩ ᰣᰦ ᰛᰬ ᰠᰩᰵ ᰛᰬ ᰠ ᰣᰤᰦ","type":"TextualBody"},"target":"https:\/\/digitalcollections.universiteitleiden.nl\/iiif_manifest\/item:335111\/canvas\/default#xywh=382,1514,2273,199"}},{"manifest":"m335106","canvas":"https:\/\/digitalcollections.universiteitleiden.nl\/iiif_manifest\/item:335111\/canvas\/default","mode":"line","line":"8","annotation":{"id":"https:\/\/digitalcollections.universiteitleiden.nl\/iiif_manifest\/item:335111\/canvas\/default\/annotation\/r8","type":"Annotation","motivation":"supplementing","body":{"text":"ᰓᰦ ᰊᰦᰮᰯ ᰜ ᰠᰪᰭ ᰌᰪᰮ ᰜᰤᰦᰵ ᰀᰦ ᰓᰦᰮ ᰓᰦ ᰑᰨ ᰀᰪᰱ ᰗᰦᰮ ᰜᰪᰵ ᰙᰫ ᰓᰦ ᰋᰦᰮ","type":"TextualBody"},"target":"https:\/\/digitalcollections.universiteitleiden.nl\/iiif_manifest\/item:335111\/canvas\/default#xywh=371,1698,2319,204"}},{"manifest":"m335106","canvas":"https:\/\/digitalcollections.universiteitleiden.nl\/iiif_manifest\/item:335111\/canvas\/default","mode":"line","line":"9","annotation":{"id":"https:\/\/digitalcollections.universiteitleiden.nl\/iiif_manifest\/item:335111\/canvas\/default\/annotation\/r9","type":"Annotation","motivation":"supplementing","body":{"text":"ᰓᰧᰭᰶ ᰋᰦᰮ ᰆᰩᰵᰶ ᰊᰪᰭ ᰉᰩᰮ ᰗᰦᰮ ᰠᰩᰳ ᰜᰪᰵ ᰓᰧ ᰋᰨ ᰅᰪᰵ ᰠ ᰇᰧᰶ ᰀᰪᰱ ᰀᰤᰩᰳ","type":"TextualBody"},"target":"https:\/\/digitalcollections.universiteitleiden.nl\/iiif_manifest\/item:335111\/canvas\/default#xywh=376,1882,2276,236"}},{"manifest":"m335106","canvas":"https:\/\/digitalcollections.universiteitleiden.nl\/iiif_manifest\/item:335111\/canvas\/default","mode":"line","line":"10","annotation":{"id":"https:\/\/digitalcollections.universiteitleiden.nl\/iiif_manifest\/item:335111\/canvas\/default\/annotation\/r10","type":"Annotation","motivation":"supplementing","body":{"text":"ᰆᰫ ᰜᰪᰵ ᰋᰦᰮ ᰓᰧᰶ ᰗᰦᰮ ᰜᰪᰵ ᰓᰧ ᰋᰨ ᰢᰪᰵ ᰠ ᰜ ᰚᰨ ᰜ ᰠᰩᰵ ᰠ","type":"TextualBody"},"target":"https:\/\/digitalcollections.universiteitleiden.nl\/iiif_manifest\/item:335111\/canvas\/default#xywh=414,2153,2221,175"}},{"manifest":"m335106","canvas":"https:\/\/digitalcollections.universiteitleiden.nl\/iiif_manifest\/item:335111\/canvas\/default","mode":"line","line":"11","annotation":{"id":"https:\/\/digitalcollections.universiteitleiden.nl\/iiif_manifest\/item:335111\/canvas\/default\/annotation\/r11","type":"Annotation","motivation":"supplementing","body":{"text":"ᰣᰦ ᰜᰨᰮ ᰃᰪᰮ ᰚᰴ ᰜᰧ ᰓᰧ ᰎᰦ ᰚᰦᰮ ᰕᰦ ᰣᰨ ᰼ ᰣᰪᰲ ᰛᰬᰰ ᰕᰧ ᰜ ᰙᰩᰵ ᰜᰪᰵ","type":"TextualBody"},"target":"https:\/\/digitalcollections.universiteitleiden.nl\/iiif_manifest\/item:335111\/canvas\/default#xywh=347,2343,2349,207"}},{"manifest":"m335106","canvas":"https:\/\/digitalcollections.universiteitleiden.nl\/iiif_manifest\/item:335111\/canvas\/default","mode":"line","line":"12","annotation":{"id":"https:\/\/digitalcollections.universiteitleiden.nl\/iiif_manifest\/item:335111\/canvas\/default\/annotation\/r12","type":"Annotation","motivation":"supplementing","body":{"text":"ᰎᰰᰶ ᰡᰬᰰ ᰜ ᰜᰤᰦᰵ ᰎᰪ ᰊᰦᰮ ᰊᰧᰮᰶ ᰕᰨ ᰀᰦᰳ ᰀᰦ ᰋᰧᰶ ᰜᰪᰵ ᰎᰰᰶ ᰡᰬᰰ ᰜ","type":"TextualBody"},"target":"https:\/\/digitalcollections.universiteitleiden.nl\/iiif_manifest\/item:335111\/canvas\/default#xywh=406,2497,2202,251"}},{"manifest":"m335106","canvas":"https:\/\/digitalcollections.universiteitleiden.nl\/iiif_manifest\/item:335111\/canvas\/default","mode":"line","line":"13","annotation":{"id":"https:\/\/digitalcollections.universiteitleiden.nl\/iiif_manifest\/item:335111\/canvas\/default\/annotation\/r13","type":"Annotation","motivation":"supplementing","body":{"text":"ᰊ ᰜᰤᰦᰵ ᰍᰪᰰ ᰎᰪᰰ ᰇᰨ ᰠ ᰜᰴ ᰌᰤᰩᰮ ᰀᰦᰳ ᰊ ᰋᰧᰭᰶ ᰜᰪᰵ ᰟᰨ ᰜᰪᰵ ᰋᰧᰶ","type":"TextualBody"},"target":"https:\/\/digitalcollections.universiteitleiden.nl\/iiif_manifest\/item:335111\/canvas\/default#xywh=388,2722,2252,228"}},{"manifest":"m335106","canvas":"https:\/\/digitalcollections.universiteitleiden.nl\/iiif_manifest\/item:335111\/canvas\/default","mode":"line","line":"14","annotation":{"id":"https:\/\/digitalcollections.universiteitleiden.nl\/iiif_manifest\/item:335111\/canvas\/default\/annotation\/r14","type":"Annotation","motivation":"supplementing","body":{"text":"ᰢᰪᰵ ᰠ ᰠ ᰃᰥᰦᰱ ᰀᰦ ᰎᰪᰰ ᰈᰨ ᰜᰦᰮ ᰋᰨ ᰅᰪᰵ ᰠ ᰣᰦ ᰀᰴ ᰀᰦ ᰕ ᰛᰩ","type":"TextualBody"},"target":"https:\/\/digitalcollections.universiteitleiden.nl\/iiif_manifest\/item:335111\/canvas\/default#xywh=376,2967,2308,181"}},{"manifest":"m335106","canvas":"https:\/\/digitalcollections.universiteitleiden.nl\/iiif_manifest\/item:335111\/canvas\/default","mode":"line","line":"15","annotation":{"id":"https:\/\/digitalcollections.universiteitleiden.nl\/iiif_manifest\/item:335111\/canvas\/default\/annotation\/r15","type":"Annotation","motivation":"supplementing","body":{"text":"ᰃᰤᰦᰮ ᰣᰨ ᰚᰨ ᰜᰪᰵ ᰕᰪᰰ ᰈᰨ ᰠ ᰣᰦ ᰀᰤᰩᰰ ᰛᰤᰬᰯ ᰜ ᰜᰳᰶ ᰜᰪᰵ ᰃᰤᰩᰳ ᰉᰩᰰ ᰍᰪᰵ","type":"TextualBody"},"target":"https:\/\/digitalcollections.universiteitleiden.nl\/iiif_manifest\/item:335111\/canvas\/default#xywh=371,3125,2325,236"}},{"manifest":"m335106","canvas":"https:\/\/digitalcollections.universiteitleiden.nl\/iiif_manifest\/item:335111\/canvas\/default","mode":"line","line":"16","annotation":{"id":"https:\/\/digitalcollections.universiteitleiden.nl\/iiif_manifest\/item:335111\/canvas\/default\/annotation\/r16","type":"Annotation","motivation":"supplementing","body":{"text":"ᰕ ᰛᰩ ᰛᰬᰯ ᰜ ᰛᰬᰯ ᰜ ᰙᰩᰭ ᰜᰪᰵ ᰕᰦᰭ ᰍᰩᰰ ᰍᰬ ᰚᰦᰮ ᰕᰦ ᰣᰨ ᰼ ᰀ ᰋᰧᰭᰶ ᰛᰬ","type":"TextualBody"},"target":"https:\/\/digitalcollections.universiteitleiden.nl\/iiif_manifest\/item:335111\/canvas\/default#xywh=394,3364,2223,230"}},{"manifest":"m335106","canvas":"https:\/\/digitalcollections.universiteitleiden.nl\/iiif_manifest\/item:335111\/canvas\/default","mode":"line","line":"17","annotation":{"id":"https:\/\/digitalcollections.universiteitleiden.nl\/iiif_manifest\/item:335111\/canvas\/default\/annotation\/r17","type":"Annotation","motivation":"supplementing","body":{"text":"ᰜ ᰀᰦ ᰎᰪᰰ ᰥᰨ ᰎᰪᰰ ᰜᰧ ᰝᰤᰬᰰ ᰕᰨ ᰊᰫᰮ ᰋᰨ ᰅᰪᰵ ᰠ ᰕ ᰛᰩ ᰀᰦᰳ","type":"TextualBody"},"target":"https:\/\/digitalcollections.universiteitleiden.nl\/iiif_manifest\/item:335111\/canvas\/default#xywh=420,3577,2276,233"}},{"manifest":"m335106","canvas":"https:\/\/digitalcollections.universiteitleiden.nl\/iiif_manifest\/item:335111\/canvas\/default","mode":"line","line":"18","annotation":{"id":"https:\/\/digitalcollections.universiteitleiden.nl\/iiif_manifest\/item:335111\/canvas\/default\/annotation\/r18","type":"Annotation","motivation":"supplementing","body":{"text":"ᰛᰤᰬᰮ ᰗᰦᰮ ᰊᰧᰮᰶ ᰅᰪᰵ ᰠ ᰗᰩᰳᰶ ᰡᰪᰵ ᰠ ᰓᰦ ᰌᰨ ᰊᰦᰮ ᰊ ᰕᰦ ᰍᰩᰰ ᰍᰬ","type":"TextualBody"},"target":"https:\/\/digitalcollections.universiteitleiden.nl\/iiif_manifest\/item:335111\/canvas\/default#xywh=438,3708,2173,306"}},{"manifest":"m335106","canvas":"https:\/\/digitalcollections.universiteitleiden.nl\/iiif_manifest\/item:335111\/canvas\/default","mode":"line","line":"19","annotation":{"id":"https:\/\/digitalcollections.universiteitleiden.nl\/iiif_manifest\/item:335111\/canvas\/default\/annotation\/r19","type":"Annotation","motivation":"supplementing","body":{"text":"ᰚᰦᰮ ᰕᰦ ᰣᰨ ᰼ ᰀᰪᰲ ᰠᰩᰵ ᰛᰬ ᰈᰪᰮ ᰙᰩᰵ ᰕᰦᰳ ᰜᰪᰵ ᰕ ᰛᰩ ᰟᰨ ᰣᰧᰳᰶ ᰊᰪᰵ ᰠ","type":"TextualBody"},"target":"https:\/\/digitalcollections.universiteitleiden.nl\/iiif_manifest\/item:335111\/canvas\/default#xywh=2926,172,2203,277"}},{"manifest":"m335106","canvas":"https:\/\/digitalcollections.universiteitleiden.nl\/iiif_manifest\/item:335111\/canvas\/default","mode":"line","line":"20","annotation":{"id":"https:\/\/digitalcollections.universiteitleiden.nl\/iiif_manifest\/item:335111\/canvas\/default\/annotation\/r20","type":"Annotation","motivation":"supplementing","body":{"text":"ᰜᰬᰰ ᰀᰪᰮ ᰓᰪ ᰊ ᰜᰪᰵ ᰕᰦ ᰜᰪᰵ ᰠᰩᰳ ᰊᰪᰵ ᰠ ᰣᰦ ᰜᰩᰮ ᰃᰪᰮ ᰚᰴ ᰌᰪᰰ","type":"TextualBody"},"target":"https:\/\/digitalcollections.universiteitleiden.nl\/iiif_manifest\/item:335111\/canvas\/default#xywh=2938,449,2185,207"}},{"manifest":"m335106","canvas":"https:\/\/digitalcollections.universiteitleiden.nl\/iiif_manifest\/item:335111\/canvas\/default","mode":"line","line":"21","annotation":{"id":"https:\/\/digitalcollections.universiteitleiden.nl\/iiif_manifest\/item:335111\/canvas\/default\/annotation\/r21","type":"Annotation","motivation":"supplementing","body":{"text":"ᰓᰧ ᰎᰦ ᰚᰦᰮ ᰕᰦ ᰣᰨ ᰼ ᰣᰨ ᰛᰬ ᰍᰪᰰ ᰀᰤᰴ ᰀᰦᰳ ᰀᰦ ᰛᰦᰯ ᰛ ᰓ ᰶ ᰀ ᰛᰪᰮ ᰚᰴ","type":"TextualBody"},"target":"https:\/\/digitalcollections.universiteitleiden.nl\/iiif_manifest\/item:335111\/canvas\/default#xywh=2882,662,2247,216"}},{"manifest":"m335106","canvas":"https:\/\/digitalcollections.universiteitleiden.nl\/iiif_manifest\/item:335111\/canvas\/default","mode":"line","line":"22","annotation":{"id":"https:\/\/digitalcollections.universiteitleiden.nl\/iiif_manifest\/item:335111\/canvas\/default\/annotation\/r22","type":"Annotation","motivation":"supplementing","body":{"text":"ᰠ ᰚᰫᰭ ᰕᰪᰰ ᰆᰧ ᰶ ᰛᰫ ᰚᰴ ᰜ ᰣᰨ ᰓᰦ ᰓᰦᰮ ᰉᰧ ᰎᰦ ᰚᰦᰮ ᰕᰦ ᰣᰨ ᰼","type":"TextualBody"},"target":"https:\/\/digitalcollections.universiteitleiden.nl\/iiif_manifest\/item:335111\/canvas\/default#xywh=2938,872,2203,193"}},{"manifest":"m335106","canvas":"https:\/\/digitalcollections.universiteitleiden.nl\/iiif_manifest\/item:335111\/canvas\/default","mode":"line","line":"23","annotation":{"id":"https:\/\/digitalcollections.universiteitleiden.nl\/iiif_manifest\/item:335111\/canvas\/default\/annotation\/r23","type":"Annotation","motivation":"supplementing","body":{"text":"ᰚᰴ ᰋᰦᰯ ᰜ ᰜᰩᰳ ᰓᰨ ᰉᰧ ᰜ ᰃᰴ ᰍ ᰛᰧᰵᰶ ᰀᰦᰮ ᰌᰪᰰ ᰓᰧ ᰓᰨ ᰣᰨ ᰀ ᰚᰫ","type":"TextualBody"},"target":"https:\/\/digitalcollections.universiteitleiden.nl\/iiif_manifest\/item:335111\/canvas\/default#xywh=2865,1074,2305,274"}},{"manifest":"m335106","canvas":"https:\/\/digitalcollections.universiteitleiden.nl\/iiif_manifest\/item:335111\/canvas\/default","mode":"line","line":"24","annotation":{"id":"https:\/\/digitalcollections.universiteitleiden.nl\/iiif_manifest\/item:335111\/canvas\/default\/annotation\/r24","type":"Annotation","motivation":"supplementing","body":{"text":"ᰎᰴ ᰍ ᰜᰤᰦᰵ ᰣᰦ ᰓᰦ ᰍᰪᰰ ᰜᰩᰳ ᰜᰪᰵ ᰕ ᰋᰩᰰ ᰍᰬ ᰚᰴ ᰜᰧ ᰓᰦᰮ ᰎᰦ ᰚᰦᰮ","type":"TextualBody"},"target":"https:\/\/digitalcollections.universiteitleiden.nl\/iiif_manifest\/item:335111\/canvas\/default#xywh=2918,1217,2231,265"}},{"manifest":"m335106","canvas":"https:\/\/digitalcollections.universiteitleiden.nl\/iiif_manifest\/item:335111\/canvas\/default","mode":"line","line":"25","annotation":{"id":"https:\/\/digitalcollections.universiteitleiden.nl\/iiif_manifest\/item:335111\/canvas\/default\/annotation\/r25","type":"Annotation","motivation":"supplementing","body":{"text":"ᰕᰦ ᰣᰨ ᰼ ᰣᰬ ᰃᰨ ᰍᰪᰰ ᰟᰤᰬᰰ ᰓᰦ ᰣᰦ ᰛᰬ ᰠᰩᰵ ᰊᰦᰯ ᰜ ᰓᰦᰮ ᰓᰦ ᰡᰫ ᰕᰳ","type":"TextualBody"},"target":"https:\/\/digitalcollections.universiteitleiden.nl\/iiif_manifest\/item:335111\/canvas\/default#xywh=2979,1444,2182,234"}},{"manifest":"m335106","canvas":"https:\/\/digitalcollections.universiteitleiden.nl\/iiif_manifest\/item:335111\/canvas\/default","mode":"line","line":"26","annotation":{"id":"https:\/\/digitalcollections.universiteitleiden.nl\/iiif_manifest\/item:335111\/canvas\/default\/annotation\/r26","type":"Annotation","motivation":"supplementing","body":{"text":"ᰊᰪᰵ ᰃᰨ ᰚᰴ ᰣᰤᰬᰳ ᰃᰬᰯ ᰜ ᰀ ᰌᰨ ᰠᰪ ᰋᰧᰵᰶ ᰌᰪᰮ ᰍᰪᰰ ᰜᰧ ᰓᰦ ᰊ ᰣᰤᰦ","type":"TextualBody"},"target":"https:\/\/digitalcollections.universiteitleiden.nl\/iiif_manifest\/item:335111\/canvas\/default#xywh=2938,1686,2173,205"}},{"manifest":"m335106","canvas":"https:\/\/digitalcollections.universiteitleiden.nl\/iiif_manifest\/item:335111\/canvas\/default","mode":"line","line":"27","annotation":{"id":"https:\/\/digitalcollections.universiteitleiden.nl\/iiif_manifest\/item:335111\/canvas\/default\/annotation\/r27","type":"Annotation","motivation":"supplementing","body":{"text":"ᰊᰦᰯ ᰜ ᰓᰦᰮ ᰓᰦ ᰊ ᰌᰨ ᰠ ᰜᰤᰦᰵ ᰀᰦ ᰓᰦᰮ ᰉᰧ ᰠ ᰋᰭ ᰀᰦ ᰕ ᰛᰩ ᰀᰦ","type":"TextualBody"},"target":"https:\/\/digitalcollections.universiteitleiden.nl\/iiif_manifest\/item:335111\/canvas\/default#xywh=2903,1888,2267,213"}},{"manifest":"m335106","canvas":"https:\/\/digitalcollections.universiteitleiden.nl\/iiif_manifest\/item:335111\/canvas\/default","mode":"line","line":"28","annotation":{"id":"https:\/\/digitalcollections.universiteitleiden.nl\/iiif_manifest\/item:335111\/canvas\/default\/annotation\/r28","type":"Annotation","motivation":"supplementing","body":{"text":"ᰀᰤᰬᰰ ᰋᰦᰭ ᰜᰪᰵ ᰎ ᰍᰨ ᰎᰪᰰ ᰌᰧ ᰠ ᰌᰤᰪ ᰜᰪᰵ ᰕᰧ ᰶ ᰠ ᰗᰦᰵ ᰀᰩ ᰃᰪᰰ","type":"TextualBody"},"target":"https:\/\/digitalcollections.universiteitleiden.nl\/iiif_manifest\/item:335111\/canvas\/default#xywh=2976,2092,2229,222"}},{"manifest":"m335106","canvas":"https:\/\/digitalcollections.universiteitleiden.nl\/iiif_manifest\/item:335111\/canvas\/default","mode":"line","line":"29","annotation":{"id":"https:\/\/digitalcollections.universiteitleiden.nl\/iiif_manifest\/item:335111\/canvas\/default\/annotation\/r29","type":"Annotation","motivation":"supplementing","body":{"text":"ᰍ ᰌᰦᰯ ᰜᰪᰵ ᰕᰦᰭ ᰀᰩᰰ ᰍᰪᰵ ᰠ ᰜ ᰚᰨ ᰜ ᰠᰩᰵ ᰜᰩᰳ ᰜᰪᰵ ᰙᰩᰰ ᰓᰦᰮ ᰕᰦ","type":"TextualBody"},"target":"https:\/\/digitalcollections.universiteitleiden.nl\/iiif_manifest\/item:335111\/canvas\/default#xywh=2935,2270,2241,245"}},{"manifest":"m335106","canvas":"https:\/\/digitalcollections.universiteitleiden.nl\/iiif_manifest\/item:335111\/canvas\/default","mode":"line","line":"30","annotation":{"id":"https:\/\/digitalcollections.universiteitleiden.nl\/iiif_manifest\/item:335111\/canvas\/default\/annotation\/r30","type":"Annotation","motivation":"supplementing","body":{"text":"ᰚᰴ ᰌᰪᰮ ᰓᰧ ᰎᰦ ᰚᰦᰮ ᰕᰦ ᰣᰨ ᰼ ᰣᰨ ᰊᰤᰬᰳ ᰀᰦ ᰠ ᰜᰤᰨ ᰚᰴ ᰜ ᰕ ᰚᰪᰰ ᰍ","type":"TextualBody"},"target":"https:\/\/digitalcollections.universiteitleiden.nl\/iiif_manifest\/item:335111\/canvas\/default#xywh=2938,2512,2214,207"}},{"manifest":"m335106","canvas":"https:\/\/digitalcollections.universiteitleiden.nl\/iiif_manifest\/item:335111\/canvas\/default","mode":"line","line":"31","annotation":{"id":"https:\/\/digitalcollections.universiteitleiden.nl\/iiif_manifest\/item:335111\/canvas\/default\/annotation\/r31","type":"Annotation","motivation":"supplementing","body":{"text":"ᰠ ᰣᰦ ᰀᰦ ᰓᰥᰦᰵ ᰕᰦ ᰀᰪ ᰠ ᰌ ᰀᰦ ᰋᰧᰰᰶ ᰍᰩᰰ ᰍᰬ ᰚᰦᰮ ᰕᰦ ᰣᰨ ᰼","type":"TextualBody"},"target":"https:\/\/digitalcollections.universiteitleiden.nl\/iiif_manifest\/item:335111\/canvas\/default#xywh=2944,2696,2232,219"}},{"manifest":"m335106","canvas":"https:\/\/digitalcollections.universiteitleiden.nl\/iiif_manifest\/item:335111\/canvas\/default","mode":"line","line":"32","annotation":{"id":"https:\/\/digitalcollections.universiteitleiden.nl\/iiif_manifest\/item:335111\/canvas\/default\/annotation\/r32","type":"Annotation","motivation":"supplementing","body":{"text":"ᰣᰨ ᰓᰦ ᰠ ᰕ ᰛᰩ ᰛᰬ ᰊᰪᰭ ᰊᰨᰮ ᰎᰩᰰ ᰓᰦᰮ ᰅᰪᰵ ᰠ ᰀᰪᰲ ᰃᰪ ᰠ ᰊᰪᰭ","type":"TextualBody"},"target":"https:\/\/digitalcollections.universiteitleiden.nl\/iiif_manifest\/item:335111\/canvas\/default#xywh=2955,2915,2148,218"}},{"manifest":"m335106","canvas":"https:\/\/digitalcollections.universiteitleiden.nl\/iiif_manifest\/item:335111\/canvas\/default","mode":"line","line":"33","annotation":{"id":"https:\/\/digitalcollections.universiteitleiden.nl\/iiif_manifest\/item:335111\/canvas\/default\/annotation\/r33","type":"Annotation","motivation":"supplementing","body":{"text":"ᰎᰪᰵ ᰀᰦ ᰣᰦ ᰕᰧᰭᰶ ᰉᰧ ᰓᰦᰮ ᰎᰦ ᰚᰦᰮ ᰕᰦ ᰣᰨ ᰼ ᰝᰪᰮ ᰚᰫ ᰠ ᰆᰧᰭᰶ","type":"TextualBody"},"target":"https:\/\/digitalcollections.universiteitleiden.nl\/iiif_manifest\/item:335111\/canvas\/default#xywh=2961,3107,2150,225"}},{"manifest":"m335106","canvas":"https:\/\/digitalcollections.universiteitleiden.nl\/iiif_manifest\/item:335111\/canvas\/default","mode":"line","line":"34","annotation":{"id":"https:\/\/digitalcollections.universiteitleiden.nl\/iiif_manifest\/item:335111\/canvas\/default\/annotation\/r34","type":"Annotation","motivation":"supplementing","body":{"text":"ᰠᰴ ᰎᰬ ᰜᰩᰮ ᰀᰩᰰ ᰍᰪᰰ ᰕ ᰛᰩ ᰛᰬ ᰎᰳᰶ ᰀᰪᰱ ᰠ ᰎᰬ ᰎᰫ ᰀᰪᰱ ᰠ ᰓᰫᰮ","type":"TextualBody"},"target":"https:\/\/digitalcollections.universiteitleiden.nl\/iiif_manifest\/item:335111\/canvas\/default#xywh=2938,3308,2220,260"}},{"manifest":"m335106","canvas":"https:\/\/digitalcollections.universiteitleiden.nl\/iiif_manifest\/item:335111\/canvas\/default","mode":"line","line":"35","annotation":{"id":"https:\/\/digitalcollections.universiteitleiden.nl\/iiif_manifest\/item:335111\/canvas\/default\/annotation\/r35","type":"Annotation","motivation":"supplementing","body":{"text":"ᰀᰩᰮ ᰍᰪᰰ ᰃᰨ ᰛᰫᰵ ᰀᰪᰱ ᰠ ᰣᰦ ᰃᰤᰦᰱ ᰕᰨ ᰀ ᰋᰧᰭᰶ ᰀᰦ ᰃᰤᰩᰮ ᰋᰨ ᰜᰪᰵ","type":"TextualBody"},"target":"https:\/\/digitalcollections.universiteitleiden.nl\/iiif_manifest\/item:335111\/canvas\/default#xywh=2900,3524,2255,216"}},{"manifest":"m335106","canvas":"https:\/\/digitalcollections.universiteitleiden.nl\/iiif_manifest\/item:335111\/canvas\/default","mode":"line","line":"36","annotation":{"id":"https:\/\/digitalcollections.universiteitleiden.nl\/iiif_manifest\/item:335111\/canvas\/default\/annotation\/r36","type":"Annotation","motivation":"supplementing","body":{"text":"ᰀᰩᰵ ᰊᰤᰫᰮ ᰋᰨ ᰛᰬ ᰙᰩᰵ ᰣᰦ ᰀ ᰀᰦ ᰗᰦᰮ ᰜᰴ ᰜᰪᰵ ᰓᰦᰮ ᰉᰧ ᰎᰦ ᰚᰦᰮ ᰕ","type":"TextualBody"},"target":"https:\/\/digitalcollections.universiteitleiden.nl\/iiif_manifest\/item:335111\/canvas\/default#xywh=2961,3688,2235,265"}}]}