{"manifest":"m335412","canvas":"https:\/\/digitalcollections.universiteitleiden.nl\/iiif_manifest\/item:335458\/canvas\/default","page":"ᰛᰪᰮ ᰓᰧ ᰚᰮ ᰣᰨ ᰼ ᰣᰨ ᰊ ᰛᰦᰭ ᰍᰦᰵ ᰛᰬ ᰛᰬ ᰃᰩᰮ ᰃᰩᰵ ᰓᰪᰰ ᰀ [1] ᰌᰧᰭᰶ ᰜᰪᰵ ᰣᰦ ᰕᰨ ᰛᰬ ᰜᰩᰭ ᰗᰦ ᰚᰮ ᰣᰨ ᰼ ᰣᰬ ᰣᰦ ᰋᰨ ᰍᰪᰰ ᰣᰦ ᰚᰪ [2] ᰛᰤᰮᰭ ᰓᰶ ᰋᰦᰭ ᰍ ᰅᰵ ᰍᰬ ᰚᰮ ᰣᰨ ᰼ ᰣᰦ ᰣᰨ ᰛᰬ ᰍᰪᰰ ᰜᰧ ᰓᰦ [3] ᰛ ᰠᰪ ᰠᰦᰭ ᰣᰤᰪ ᰎᰩᰰᰶ ᰛᰪᰱ ᰛᰬ ᰕ ᰛᰩ ᰃᰪᰰ ᰍ ᰠ ᰜᰬᰰᰶ ᰜ [4] ᰛᰤᰫ ᰛᰤᰦᰮ ᰅᰪᰵ ᰃᰩ ᰚᰦᰵ ᰜ ᰠ ᰛᰧᰵᰶ ᰃᰨ ᰅᰰᰶ ᰓᰦ ᰛᰬ ᰣᰦ ᰛᰬ [5] ᰙᰩᰵ ᰬᰰᰶ ᰍᰩᰵᰶ ᰍᰪᰵ ᰛᰬ ᰚᰴ ᰜᰧ ᰓᰦ ᰝᰥᰮ ᰚᰮ ᰣᰨ ᰼ ᰛᰬ ᰗᰦ ᰠᰪ [6] ᰠ ᰛᰪᰰ ᰛᰩᰵᰶ ᰎᰩ ᰚᰴ ᰌᰦ ᰜᰧ ᰓᰦ ᰝᰥᰩᰱ ᰛᰩ ᰍᰩᰰ ᰍᰬ ᰚᰮ ᰣᰨ [7] ᰼ ᰎᰫ ᰎᰨ ᰍᰦᰵ ᰠᰬ ᰠ ᰓᰦ ᰍᰩᰵ ᰅᰪᰵ ᰃᰩ ᰚᰴ ᰜᰧ ᰚᰮ ᰓᰨ ᰼ [8] ᰣᰤᰪ ᰕᰩ ᰚᰪᰱ ᰛᰬ ᰈᰫᰮ ᰜ ᰃᰤᰬᰰ ᰓᰦᰰ ᰣᰦ ᰜᰨ ᰚᰴ ᰡᰪᰵ ᰚᰮ ᰣᰨ ᰼ [9] ᰆᰧᰬᰰ ᰓᰨ ᰅᰨᰵᰶ ᰣᰦ ᰉᰧ ᰛᰬ ᰜ ᰠ ᰛᰩᰵᰶ ᰋᰫᰵ ᰓᰦᰧ ᰕ ᰓᰪᰵ ᰜ ᰛᰤᰫ [10] ᰛᰦᰮ ᰜ ᰕᰦᰳ ᰜᰪᰵ ᰓᰦᰮ ᰕ ᰣᰨ ᰼ ᰠᰪ ᰠᰦᰭ ᰃᰧᰰ ᰓᰪᰱ [11] ᰜ ᰛᰤᰫ ᰜ ᰕᰦᰳ ᰜᰪᰵ ᰃᰴ ᰓᰦᰮ ᰓᰨ ᰣᰨ ᰼ ᰍᰦᰵ ᰃᰬᰰ ᰍᰪᰰ ᰣᰨ [12] ᰜ ᰜᰨ ᰚᰴ ᰜᰧ ᰚᰮ ᰣᰨ ᰼ ᰝᰦᰰ ᰣᰦ ᰕᰨ ᰛᰬ ᰝᰩ ᰎᰫ [13] ᰚᰴ ᰠᰦᰭ ᰆᰧᰵᰶ ᰓᰦᰰ ᰼ ᰍᰦᰵ ᰛᰬ ᰛᰬ ᰂᰦᰰ ᰛᰨ ᰅᰨ ᰠ ᰣᰦ [14] ᰆᰩᰮ ᰓᰧ ᰅᰪᰵ ᰠ ᰣᰦ ᰋᰩᰭ ᰍᰪᰰ ᰃᰦᰮ ᰎᰨ ᰶᰵᰶ ᰠᰦᰭ ᰅᰫᰰ ᰓᰪ [15] ᰌᰧᰶ ᰜᰪᰵ ᰣᰦ ᰣᰨ ᰛᰤᰬᰮ ᰓᰧ ᰚᰮ ᰣᰨ ᰼ ᰛᰬ ᰣᰨ ᰊ ᰛᰦ [16] ᰣᰦ ᰅᰨ ᰛᰬ ᰍᰪᰰ ᰓᰪᰮ ᰋᰧᰶ ᰅᰪᰵ ᰠ ᰓᰫ ᰛᰤᰫ ᰍᰩᰰ ᰍᰬ ᰚᰮ ᰣᰨ ᰼ [17] ᰛ ᰠᰪ ᰠ ᰜ ᰣᰤᰪ ᰎᰩᰰ ᰌᰪᰱ ᰛᰬ ᰃᰪᰰ ᰍ ᰠ ᰜᰬᰰᰶ ᰜ ᰛᰤᰫ ᰛᰤᰦ [18] ᰅᰪᰵ ᰃᰨ ᰂᰦ ᰜ ᰠ ᰛᰨᰵᰶ ᰃᰨ ᰅᰭᰶ ᰓᰦ ᰣᰦᰵ ᰛᰬ ᰡᰴ ᰈᰬᰰ ᰍᰩᰰ ᰍᰪᰵ ᰛᰬ ᰚᰴ [19] ᰜᰧ ᰚᰮ ᰣᰨ ᰼ ᰬ ᰀ ᰠᰪ ᰌᰪᰮ ᰎᰨ ᰚᰴ ᰜᰧ ᰋᰨᰵ ᰓᰦᰰ ᰝᰥᰵᰶ ᰅᰮᰶ [20] ᰣᰨ ᰼ ᰝᰦ ᰣᰦ ᰛᰪᰰ ᰍᰪᰰ ᰣᰦ ᰅᰨ ᰀᰦ ᰡᰪᰵ ᰚᰮᰶ ᰣᰨ ᰼ [21] ᰣᰦ ᰅᰨ ᰢᰩᰵ ᰣᰦ ᰜᰴ ᰗᰦ ᰅᰨ ᰃᰩ ᰃᰩ ᰛᰧᰶ ᰜ ᰕᰦᰭ [22] ᰜᰪᰵ ᰜᰤᰦᰵ ᰢᰫᰵ ᰛᰦ ᰜᰦᰰ ᰚ ᰚᰮ ᰣᰨ ᰼ ᰓ ᰕᰧᰶ [23] ᰠ ᰎᰦ ᰓᰫᰵ ᰠ ᰣᰦ ᰊᰪᰭ ᰀᰦ ᰛᰤᰬ ᰛᰤᰦᰵ ᰜ [24] ᰎᰦ ᰜᰪᰵ ᰃᰧ ᰛᰦ ᰃᰦᰵ ᰣᰨ ᰼ ᰅ ᰶ ᰣᰦ ᰓᰨ ᰣᰦ ᰋᰴ [25] ᰣᰦ ᰛᰧᰵᰶ ᰛᰬᰰ ᰜ ᰅ ᰓᰪ ᰍᰩᰵ ᰜ ᰕᰦᰳ ᰜᰪᰵ ᰓᰦᰮ ᰕ ᰛᰨ [26] ᰼ ᰚᰦ  ᰃᰥᰧ ᰣᰤᰪ ᰚᰴ ᰜᰧ ᰠ ᰕ ᰉᰧᰰᰶ ᰍ ᰼ [27] ᰦᰭ ᰣᰨ ᰼ ᰋᰦᰮ ᰜᰨᰶ ᰋᰦᰮ ᰓᰪ ᰃᰪᰰ ᰗᰦ ᰛᰨᰵᰶ ᰜ [28] ᰕᰳ ᰣᰨ ᰼ ᰍᰫᰭ ᰃᰴᰧ ᰜᰩᰵ ᰛᰦ ᰕ ᰃᰦᰵ ᰍ ᰕᰦᰳᰶ ᰜ [29] ᰅᰨ ᰚᰴ ᰜᰧ ᰓᰧ ᰚᰮ ᰣᰨ ᰼ ᰬ ᰅ ᰛᰩ ᰀᰦ ᰣᰦ ᰙᰩᰵ ᰣᰦ [30] ᰋᰤᰧᰰ ᰓᰧᰰᰶ ᰍ ᰜ ᰕᰦᰳ ᰣᰨ ᰼ ᰣᰬ ᰍᰦᰵ ᰠᰬ ᰃᰨ ᰪ ᰛᰧᰰᰶ [31] ᰠ ᰜᰤᰦᰵ ᰌᰦ ᰜᰩᰰ ᰍᰩᰰ ᰕ ᰣᰨ ᰼ ᰚᰨ ᰜ ᰓᰧ ᰓᰦᰵ ᰃᰬ [32] ᰛᰬ ᰓᰫᰵ ᰜ ᰕ ᰃᰧᰰᰶ ᰍ ᰅᰦ ᰜᰪᰵ ᰜᰧ ᰀᰦ ᰜᰩ ᰍᰩᰰ ᰡᰴ ᰕᰦᰳ [33] ᰜᰪᰵ ᰅᰦᰰ ᰌᰧ ᰅᰬ ᰛᰦ ᰼ ᰛᰬ ᰣ ᰓᰦ ᰕᰨ ᰠ ᰎᰪᰰ ᰣᰤᰫᰭ [34] ","annotations":[{"manifest":"m335412","canvas":"https:\/\/digitalcollections.universiteitleiden.nl\/iiif_manifest\/item:335458\/canvas\/default","mode":"line","line":"1","annotation":{"id":"https:\/\/digitalcollections.universiteitleiden.nl\/iiif_manifest\/item:335458\/canvas\/default\/annotation\/r1","type":"Annotation","motivation":"supplementing","body":{"text":"ᰛᰪᰮ ᰓᰧ ᰚᰮ ᰣᰨ ᰼ ᰣᰨ ᰊ ᰛᰦᰭ ᰍᰦᰵ ᰛᰬ ᰛᰬ ᰃᰩᰮ ᰃᰩᰵ ᰓᰪᰰ ᰀ","type":"TextualBody"},"target":"https:\/\/digitalcollections.universiteitleiden.nl\/iiif_manifest\/item:335458\/canvas\/default#xywh=468,393,2138,240"}},{"manifest":"m335412","canvas":"https:\/\/digitalcollections.universiteitleiden.nl\/iiif_manifest\/item:335458\/canvas\/default","mode":"line","line":"2","annotation":{"id":"https:\/\/digitalcollections.universiteitleiden.nl\/iiif_manifest\/item:335458\/canvas\/default\/annotation\/r2","type":"Annotation","motivation":"supplementing","body":{"text":"ᰌᰧᰭᰶ ᰜᰪᰵ ᰣᰦ ᰕᰨ ᰛᰬ ᰜᰩᰭ ᰗᰦ ᰚᰮ ᰣᰨ ᰼ ᰣᰬ ᰣᰦ ᰋᰨ ᰍᰪᰰ ᰣᰦ ᰚᰪ","type":"TextualBody"},"target":"https:\/\/digitalcollections.universiteitleiden.nl\/iiif_manifest\/item:335458\/canvas\/default#xywh=433,607,2296,248"}},{"manifest":"m335412","canvas":"https:\/\/digitalcollections.universiteitleiden.nl\/iiif_manifest\/item:335458\/canvas\/default","mode":"line","line":"3","annotation":{"id":"https:\/\/digitalcollections.universiteitleiden.nl\/iiif_manifest\/item:335458\/canvas\/default\/annotation\/r3","type":"Annotation","motivation":"supplementing","body":{"text":"ᰛᰤᰮᰭ ᰓᰶ ᰋᰦᰭ ᰍ ᰅᰵ ᰍᰬ ᰚᰮ ᰣᰨ ᰼ ᰣᰦ ᰣᰨ ᰛᰬ ᰍᰪᰰ ᰜᰧ ᰓᰦ","type":"TextualBody"},"target":"https:\/\/digitalcollections.universiteitleiden.nl\/iiif_manifest\/item:335458\/canvas\/default#xywh=462,838,2138,248"}},{"manifest":"m335412","canvas":"https:\/\/digitalcollections.universiteitleiden.nl\/iiif_manifest\/item:335458\/canvas\/default","mode":"line","line":"4","annotation":{"id":"https:\/\/digitalcollections.universiteitleiden.nl\/iiif_manifest\/item:335458\/canvas\/default\/annotation\/r4","type":"Annotation","motivation":"supplementing","body":{"text":"ᰛ ᰠᰪ ᰠᰦᰭ ᰣᰤᰪ ᰎᰩᰰᰶ ᰛᰪᰱ ᰛᰬ ᰕ ᰛᰩ ᰃᰪᰰ ᰍ ᰠ ᰜᰬᰰᰶ ᰜ","type":"TextualBody"},"target":"https:\/\/digitalcollections.universiteitleiden.nl\/iiif_manifest\/item:335458\/canvas\/default#xywh=448,1069,2118,231"}},{"manifest":"m335412","canvas":"https:\/\/digitalcollections.universiteitleiden.nl\/iiif_manifest\/item:335458\/canvas\/default","mode":"line","line":"5","annotation":{"id":"https:\/\/digitalcollections.universiteitleiden.nl\/iiif_manifest\/item:335458\/canvas\/default\/annotation\/r5","type":"Annotation","motivation":"supplementing","body":{"text":"ᰛᰤᰫ ᰛᰤᰦᰮ ᰅᰪᰵ ᰃᰩ ᰚᰦᰵ ᰜ ᰠ ᰛᰧᰵᰶ ᰃᰨ ᰅᰰᰶ ᰓᰦ ᰛᰬ ᰣᰦ ᰛᰬ","type":"TextualBody"},"target":"https:\/\/digitalcollections.universiteitleiden.nl\/iiif_manifest\/item:335458\/canvas\/default#xywh=462,1252,2121,253"}},{"manifest":"m335412","canvas":"https:\/\/digitalcollections.universiteitleiden.nl\/iiif_manifest\/item:335458\/canvas\/default","mode":"line","line":"6","annotation":{"id":"https:\/\/digitalcollections.universiteitleiden.nl\/iiif_manifest\/item:335458\/canvas\/default\/annotation\/r6","type":"Annotation","motivation":"supplementing","body":{"text":"ᰙᰩᰵ ᰬᰰᰶ ᰍᰩᰵᰶ ᰍᰪᰵ ᰛᰬ ᰚᰴ ᰜᰧ ᰓᰦ ᰝᰥᰮ ᰚᰮ ᰣᰨ ᰼ ᰛᰬ ᰗᰦ ᰠᰪ","type":"TextualBody"},"target":"https:\/\/digitalcollections.universiteitleiden.nl\/iiif_manifest\/item:335458\/canvas\/default#xywh=408,1466,2167,242"}},{"manifest":"m335412","canvas":"https:\/\/digitalcollections.universiteitleiden.nl\/iiif_manifest\/item:335458\/canvas\/default","mode":"line","line":"7","annotation":{"id":"https:\/\/digitalcollections.universiteitleiden.nl\/iiif_manifest\/item:335458\/canvas\/default\/annotation\/r7","type":"Annotation","motivation":"supplementing","body":{"text":"ᰠ ᰛᰪᰰ ᰛᰩᰵᰶ ᰎᰩ ᰚᰴ ᰌᰦ ᰜᰧ ᰓᰦ ᰝᰥᰩᰱ ᰛᰩ ᰍᰩᰰ ᰍᰬ ᰚᰮ ᰣᰨ","type":"TextualBody"},"target":"https:\/\/digitalcollections.universiteitleiden.nl\/iiif_manifest\/item:335458\/canvas\/default#xywh=488,1674,2058,233"}},{"manifest":"m335412","canvas":"https:\/\/digitalcollections.universiteitleiden.nl\/iiif_manifest\/item:335458\/canvas\/default","mode":"line","line":"8","annotation":{"id":"https:\/\/digitalcollections.universiteitleiden.nl\/iiif_manifest\/item:335458\/canvas\/default\/annotation\/r8","type":"Annotation","motivation":"supplementing","body":{"text":"᰼ ᰎᰫ ᰎᰨ ᰍᰦᰵ ᰠᰬ ᰠ ᰓᰦ ᰍᰩᰵ ᰅᰪᰵ ᰃᰩ ᰚᰴ ᰜᰧ ᰚᰮ ᰓᰨ ᰼","type":"TextualBody"},"target":"https:\/\/digitalcollections.universiteitleiden.nl\/iiif_manifest\/item:335458\/canvas\/default#xywh=465,1907,2184,203"}},{"manifest":"m335412","canvas":"https:\/\/digitalcollections.universiteitleiden.nl\/iiif_manifest\/item:335458\/canvas\/default","mode":"line","line":"9","annotation":{"id":"https:\/\/digitalcollections.universiteitleiden.nl\/iiif_manifest\/item:335458\/canvas\/default\/annotation\/r9","type":"Annotation","motivation":"supplementing","body":{"text":"ᰣᰤᰪ ᰕᰩ ᰚᰪᰱ ᰛᰬ ᰈᰫᰮ ᰜ ᰃᰤᰬᰰ ᰓᰦᰰ ᰣᰦ ᰜᰨ ᰚᰴ ᰡᰪᰵ ᰚᰮ ᰣᰨ ᰼","type":"TextualBody"},"target":"https:\/\/digitalcollections.universiteitleiden.nl\/iiif_manifest\/item:335458\/canvas\/default#xywh=450,2087,2230,240"}},{"manifest":"m335412","canvas":"https:\/\/digitalcollections.universiteitleiden.nl\/iiif_manifest\/item:335458\/canvas\/default","mode":"line","line":"10","annotation":{"id":"https:\/\/digitalcollections.universiteitleiden.nl\/iiif_manifest\/item:335458\/canvas\/default\/annotation\/r10","type":"Annotation","motivation":"supplementing","body":{"text":"ᰆᰧᰬᰰ ᰓᰨ ᰅᰨᰵᰶ ᰣᰦ ᰉᰧ ᰛᰬ ᰜ ᰠ ᰛᰩᰵᰶ ᰋᰫᰵ ᰓᰦᰧ ᰕ ᰓᰪᰵ ᰜ ᰛᰤᰫ","type":"TextualBody"},"target":"https:\/\/digitalcollections.universiteitleiden.nl\/iiif_manifest\/item:335458\/canvas\/default#xywh=459,2341,2158,197"}},{"manifest":"m335412","canvas":"https:\/\/digitalcollections.universiteitleiden.nl\/iiif_manifest\/item:335458\/canvas\/default","mode":"line","line":"11","annotation":{"id":"https:\/\/digitalcollections.universiteitleiden.nl\/iiif_manifest\/item:335458\/canvas\/default\/annotation\/r11","type":"Annotation","motivation":"supplementing","body":{"text":"ᰛᰦᰮ ᰜ ᰕᰦᰳ ᰜᰪᰵ ᰓᰦᰮ ᰕ ᰣᰨ ᰼ ᰠᰪ ᰠᰦᰭ ᰃᰧᰰ ᰓᰪᰱ","type":"TextualBody"},"target":"https:\/\/digitalcollections.universiteitleiden.nl\/iiif_manifest\/item:335458\/canvas\/default#xywh=482,2506,2153,251"}},{"manifest":"m335412","canvas":"https:\/\/digitalcollections.universiteitleiden.nl\/iiif_manifest\/item:335458\/canvas\/default","mode":"line","line":"12","annotation":{"id":"https:\/\/digitalcollections.universiteitleiden.nl\/iiif_manifest\/item:335458\/canvas\/default\/annotation\/r12","type":"Annotation","motivation":"supplementing","body":{"text":"ᰜ ᰛᰤᰫ ᰜ ᰕᰦᰳ ᰜᰪᰵ ᰃᰴ ᰓᰦᰮ ᰓᰨ ᰣᰨ ᰼ ᰍᰦᰵ ᰃᰬᰰ ᰍᰪᰰ ᰣᰨ","type":"TextualBody"},"target":"https:\/\/digitalcollections.universiteitleiden.nl\/iiif_manifest\/item:335458\/canvas\/default#xywh=533,2729,2042,236"}},{"manifest":"m335412","canvas":"https:\/\/digitalcollections.universiteitleiden.nl\/iiif_manifest\/item:335458\/canvas\/default","mode":"line","line":"13","annotation":{"id":"https:\/\/digitalcollections.universiteitleiden.nl\/iiif_manifest\/item:335458\/canvas\/default\/annotation\/r13","type":"Annotation","motivation":"supplementing","body":{"text":"ᰜ ᰜᰨ ᰚᰴ ᰜᰧ ᰚᰮ ᰣᰨ ᰼ ᰝᰦᰰ ᰣᰦ ᰕᰨ ᰛᰬ ᰝᰩ ᰎᰫ","type":"TextualBody"},"target":"https:\/\/digitalcollections.universiteitleiden.nl\/iiif_manifest\/item:335458\/canvas\/default#xywh=485,2928,2055,245"}},{"manifest":"m335412","canvas":"https:\/\/digitalcollections.universiteitleiden.nl\/iiif_manifest\/item:335458\/canvas\/default","mode":"line","line":"14","annotation":{"id":"https:\/\/digitalcollections.universiteitleiden.nl\/iiif_manifest\/item:335458\/canvas\/default\/annotation\/r14","type":"Annotation","motivation":"supplementing","body":{"text":"ᰚᰴ ᰠᰦᰭ ᰆᰧᰵᰶ ᰓᰦᰰ ᰼ ᰍᰦᰵ ᰛᰬ ᰛᰬ ᰂᰦᰰ ᰛᰨ ᰅᰨ ᰠ ᰣᰦ","type":"TextualBody"},"target":"https:\/\/digitalcollections.universiteitleiden.nl\/iiif_manifest\/item:335458\/canvas\/default#xywh=485,3159,2112,220"}},{"manifest":"m335412","canvas":"https:\/\/digitalcollections.universiteitleiden.nl\/iiif_manifest\/item:335458\/canvas\/default","mode":"line","line":"15","annotation":{"id":"https:\/\/digitalcollections.universiteitleiden.nl\/iiif_manifest\/item:335458\/canvas\/default\/annotation\/r15","type":"Annotation","motivation":"supplementing","body":{"text":"ᰆᰩᰮ ᰓᰧ ᰅᰪᰵ ᰠ ᰣᰦ ᰋᰩᰭ ᰍᰪᰰ ᰃᰦᰮ ᰎᰨ ᰶᰵᰶ ᰠᰦᰭ ᰅᰫᰰ ᰓᰪ","type":"TextualBody"},"target":"https:\/\/digitalcollections.universiteitleiden.nl\/iiif_manifest\/item:335458\/canvas\/default#xywh=431,3325,2095,253"}},{"manifest":"m335412","canvas":"https:\/\/digitalcollections.universiteitleiden.nl\/iiif_manifest\/item:335458\/canvas\/default","mode":"line","line":"16","annotation":{"id":"https:\/\/digitalcollections.universiteitleiden.nl\/iiif_manifest\/item:335458\/canvas\/default\/annotation\/r16","type":"Annotation","motivation":"supplementing","body":{"text":"ᰌᰧᰶ ᰜᰪᰵ ᰣᰦ ᰣᰨ ᰛᰤᰬᰮ ᰓᰧ ᰚᰮ ᰣᰨ ᰼ ᰛᰬ ᰣᰨ ᰊ ᰛᰦ","type":"TextualBody"},"target":"https:\/\/digitalcollections.universiteitleiden.nl\/iiif_manifest\/item:335458\/canvas\/default#xywh=442,3570,1987,242"}},{"manifest":"m335412","canvas":"https:\/\/digitalcollections.universiteitleiden.nl\/iiif_manifest\/item:335458\/canvas\/default","mode":"line","line":"17","annotation":{"id":"https:\/\/digitalcollections.universiteitleiden.nl\/iiif_manifest\/item:335458\/canvas\/default\/annotation\/r17","type":"Annotation","motivation":"supplementing","body":{"text":"ᰣᰦ ᰅᰨ ᰛᰬ ᰍᰪᰰ ᰓᰪᰮ ᰋᰧᰶ ᰅᰪᰵ ᰠ ᰓᰫ ᰛᰤᰫ ᰍᰩᰰ ᰍᰬ ᰚᰮ ᰣᰨ ᰼","type":"TextualBody"},"target":"https:\/\/digitalcollections.universiteitleiden.nl\/iiif_manifest\/item:335458\/canvas\/default#xywh=436,3758,2124,308"}},{"manifest":"m335412","canvas":"https:\/\/digitalcollections.universiteitleiden.nl\/iiif_manifest\/item:335458\/canvas\/default","mode":"line","line":"18","annotation":{"id":"https:\/\/digitalcollections.universiteitleiden.nl\/iiif_manifest\/item:335458\/canvas\/default\/annotation\/r18","type":"Annotation","motivation":"supplementing","body":{"text":"ᰛ ᰠᰪ ᰠ ᰜ ᰣᰤᰪ ᰎᰩᰰ ᰌᰪᰱ ᰛᰬ ᰃᰪᰰ ᰍ ᰠ ᰜᰬᰰᰶ ᰜ ᰛᰤᰫ ᰛᰤᰦ","type":"TextualBody"},"target":"https:\/\/digitalcollections.universiteitleiden.nl\/iiif_manifest\/item:335458\/canvas\/default#xywh=3028,431,2170,208"}},{"manifest":"m335412","canvas":"https:\/\/digitalcollections.universiteitleiden.nl\/iiif_manifest\/item:335458\/canvas\/default","mode":"line","line":"19","annotation":{"id":"https:\/\/digitalcollections.universiteitleiden.nl\/iiif_manifest\/item:335458\/canvas\/default\/annotation\/r19","type":"Annotation","motivation":"supplementing","body":{"text":"ᰅᰪᰵ ᰃᰨ ᰂᰦ ᰜ ᰠ ᰛᰨᰵᰶ ᰃᰨ ᰅᰭᰶ ᰓᰦ ᰣᰦᰵ ᰛᰬ ᰡᰴ ᰈᰬᰰ ᰍᰩᰰ ᰍᰪᰵ ᰛᰬ ᰚᰴ","type":"TextualBody"},"target":"https:\/\/digitalcollections.universiteitleiden.nl\/iiif_manifest\/item:335458\/canvas\/default#xywh=3022,656,2187,248"}},{"manifest":"m335412","canvas":"https:\/\/digitalcollections.universiteitleiden.nl\/iiif_manifest\/item:335458\/canvas\/default","mode":"line","line":"20","annotation":{"id":"https:\/\/digitalcollections.universiteitleiden.nl\/iiif_manifest\/item:335458\/canvas\/default\/annotation\/r20","type":"Annotation","motivation":"supplementing","body":{"text":"ᰜᰧ ᰚᰮ ᰣᰨ ᰼ ᰬ ᰀ ᰠᰪ ᰌᰪᰮ ᰎᰨ ᰚᰴ ᰜᰧ ᰋᰨᰵ ᰓᰦᰰ ᰝᰥᰵᰶ ᰅᰮᰶ","type":"TextualBody"},"target":"https:\/\/digitalcollections.universiteitleiden.nl\/iiif_manifest\/item:335458\/canvas\/default#xywh=3022,793,2164,293"}},{"manifest":"m335412","canvas":"https:\/\/digitalcollections.universiteitleiden.nl\/iiif_manifest\/item:335458\/canvas\/default","mode":"line","line":"21","annotation":{"id":"https:\/\/digitalcollections.universiteitleiden.nl\/iiif_manifest\/item:335458\/canvas\/default\/annotation\/r21","type":"Annotation","motivation":"supplementing","body":{"text":"ᰣᰨ ᰼ ᰝᰦ ᰣᰦ ᰛᰪᰰ ᰍᰪᰰ ᰣᰦ ᰅᰨ ᰀᰦ ᰡᰪᰵ ᰚᰮᰶ ᰣᰨ ᰼","type":"TextualBody"},"target":"https:\/\/digitalcollections.universiteitleiden.nl\/iiif_manifest\/item:335458\/canvas\/default#xywh=3034,1081,2201,205"}},{"manifest":"m335412","canvas":"https:\/\/digitalcollections.universiteitleiden.nl\/iiif_manifest\/item:335458\/canvas\/default","mode":"line","line":"22","annotation":{"id":"https:\/\/digitalcollections.universiteitleiden.nl\/iiif_manifest\/item:335458\/canvas\/default\/annotation\/r22","type":"Annotation","motivation":"supplementing","body":{"text":"ᰣᰦ ᰅᰨ ᰢᰩᰵ ᰣᰦ ᰜᰴ ᰗᰦ ᰅᰨ ᰃᰩ ᰃᰩ ᰛᰧᰶ ᰜ ᰕᰦᰭ","type":"TextualBody"},"target":"https:\/\/digitalcollections.universiteitleiden.nl\/iiif_manifest\/item:335458\/canvas\/default#xywh=3071,1280,2056,217"}},{"manifest":"m335412","canvas":"https:\/\/digitalcollections.universiteitleiden.nl\/iiif_manifest\/item:335458\/canvas\/default","mode":"line","line":"23","annotation":{"id":"https:\/\/digitalcollections.universiteitleiden.nl\/iiif_manifest\/item:335458\/canvas\/default\/annotation\/r23","type":"Annotation","motivation":"supplementing","body":{"text":"ᰜᰪᰵ ᰜᰤᰦᰵ ᰢᰫᰵ ᰛᰦ ᰜᰦᰰ ᰚ ᰚᰮ ᰣᰨ ᰼ ᰓ ᰕᰧᰶ","type":"TextualBody"},"target":"https:\/\/digitalcollections.universiteitleiden.nl\/iiif_manifest\/item:335458\/canvas\/default#xywh=3099,1511,1999,217"}},{"manifest":"m335412","canvas":"https:\/\/digitalcollections.universiteitleiden.nl\/iiif_manifest\/item:335458\/canvas\/default","mode":"line","line":"24","annotation":{"id":"https:\/\/digitalcollections.universiteitleiden.nl\/iiif_manifest\/item:335458\/canvas\/default\/annotation\/r24","type":"Annotation","motivation":"supplementing","body":{"text":"ᰠ ᰎᰦ ᰓᰫᰵ ᰠ ᰣᰦ ᰊᰪᰭ ᰀᰦ ᰛᰤᰬ ᰛᰤᰦᰵ ᰜ","type":"TextualBody"},"target":"https:\/\/digitalcollections.universiteitleiden.nl\/iiif_manifest\/item:335458\/canvas\/default#xywh=3116,1711,1985,211"}},{"manifest":"m335412","canvas":"https:\/\/digitalcollections.universiteitleiden.nl\/iiif_manifest\/item:335458\/canvas\/default","mode":"line","line":"25","annotation":{"id":"https:\/\/digitalcollections.universiteitleiden.nl\/iiif_manifest\/item:335458\/canvas\/default\/annotation\/r25","type":"Annotation","motivation":"supplementing","body":{"text":"ᰎᰦ ᰜᰪᰵ ᰃᰧ ᰛᰦ ᰃᰦᰵ ᰣᰨ ᰼ ᰅ ᰶ ᰣᰦ ᰓᰨ ᰣᰦ ᰋᰴ","type":"TextualBody"},"target":"https:\/\/digitalcollections.universiteitleiden.nl\/iiif_manifest\/item:335458\/canvas\/default#xywh=3071,1925,2067,211"}},{"manifest":"m335412","canvas":"https:\/\/digitalcollections.universiteitleiden.nl\/iiif_manifest\/item:335458\/canvas\/default","mode":"line","line":"26","annotation":{"id":"https:\/\/digitalcollections.universiteitleiden.nl\/iiif_manifest\/item:335458\/canvas\/default\/annotation\/r26","type":"Annotation","motivation":"supplementing","body":{"text":"ᰣᰦ ᰛᰧᰵᰶ ᰛᰬᰰ ᰜ ᰅ ᰓᰪ ᰍᰩᰵ ᰜ ᰕᰦᰳ ᰜᰪᰵ ᰓᰦᰮ ᰕ ᰛᰨ","type":"TextualBody"},"target":"https:\/\/digitalcollections.universiteitleiden.nl\/iiif_manifest\/item:335458\/canvas\/default#xywh=3105,2121,2004,223"}},{"manifest":"m335412","canvas":"https:\/\/digitalcollections.universiteitleiden.nl\/iiif_manifest\/item:335458\/canvas\/default","mode":"line","line":"27","annotation":{"id":"https:\/\/digitalcollections.universiteitleiden.nl\/iiif_manifest\/item:335458\/canvas\/default\/annotation\/r27","type":"Annotation","motivation":"supplementing","body":{"text":"᰼ ᰚᰦ  ᰃᰥᰧ ᰣᰤᰪ ᰚᰴ ᰜᰧ ᰠ ᰕ ᰉᰧᰰᰶ ᰍ ᰼","type":"TextualBody"},"target":"https:\/\/digitalcollections.universiteitleiden.nl\/iiif_manifest\/item:335458\/canvas\/default#xywh=3065,2324,2099,225"}},{"manifest":"m335412","canvas":"https:\/\/digitalcollections.universiteitleiden.nl\/iiif_manifest\/item:335458\/canvas\/default","mode":"line","line":"28","annotation":{"id":"https:\/\/digitalcollections.universiteitleiden.nl\/iiif_manifest\/item:335458\/canvas\/default\/annotation\/r28","type":"Annotation","motivation":"supplementing","body":{"text":"ᰦᰭ ᰣᰨ ᰼ ᰋᰦᰮ ᰜᰨᰶ ᰋᰦᰮ ᰓᰪ ᰃᰪᰰ ᰗᰦ ᰛᰨᰵᰶ ᰜ","type":"TextualBody"},"target":"https:\/\/digitalcollections.universiteitleiden.nl\/iiif_manifest\/item:335458\/canvas\/default#xywh=3131,2515,2121,216"}},{"manifest":"m335412","canvas":"https:\/\/digitalcollections.universiteitleiden.nl\/iiif_manifest\/item:335458\/canvas\/default","mode":"line","line":"29","annotation":{"id":"https:\/\/digitalcollections.universiteitleiden.nl\/iiif_manifest\/item:335458\/canvas\/default\/annotation\/r29","type":"Annotation","motivation":"supplementing","body":{"text":"ᰕᰳ ᰣᰨ ᰼ ᰍᰫᰭ ᰃᰴᰧ ᰜᰩᰵ ᰛᰦ ᰕ ᰃᰦᰵ ᰍ ᰕᰦᰳᰶ ᰜ","type":"TextualBody"},"target":"https:\/\/digitalcollections.universiteitleiden.nl\/iiif_manifest\/item:335458\/canvas\/default#xywh=3171,2720,1995,280"}},{"manifest":"m335412","canvas":"https:\/\/digitalcollections.universiteitleiden.nl\/iiif_manifest\/item:335458\/canvas\/default","mode":"line","line":"30","annotation":{"id":"https:\/\/digitalcollections.universiteitleiden.nl\/iiif_manifest\/item:335458\/canvas\/default\/annotation\/r30","type":"Annotation","motivation":"supplementing","body":{"text":"ᰅᰨ ᰚᰴ ᰜᰧ ᰓᰧ ᰚᰮ ᰣᰨ ᰼ ᰬ ᰅ ᰛᰩ ᰀᰦ ᰣᰦ ᰙᰩᰵ ᰣᰦ","type":"TextualBody"},"target":"https:\/\/digitalcollections.universiteitleiden.nl\/iiif_manifest\/item:335458\/canvas\/default#xywh=3071,2957,2135,205"}},{"manifest":"m335412","canvas":"https:\/\/digitalcollections.universiteitleiden.nl\/iiif_manifest\/item:335458\/canvas\/default","mode":"line","line":"31","annotation":{"id":"https:\/\/digitalcollections.universiteitleiden.nl\/iiif_manifest\/item:335458\/canvas\/default\/annotation\/r31","type":"Annotation","motivation":"supplementing","body":{"text":"ᰋᰤᰧᰰ ᰓᰧᰰᰶ ᰍ ᰜ ᰕᰦᰳ ᰣᰨ ᰼ ᰣᰬ ᰍᰦᰵ ᰠᰬ ᰃᰨ ᰪ ᰛᰧᰰᰶ","type":"TextualBody"},"target":"https:\/\/digitalcollections.universiteitleiden.nl\/iiif_manifest\/item:335458\/canvas\/default#xywh=3131,3168,2112,271"}},{"manifest":"m335412","canvas":"https:\/\/digitalcollections.universiteitleiden.nl\/iiif_manifest\/item:335458\/canvas\/default","mode":"line","line":"32","annotation":{"id":"https:\/\/digitalcollections.universiteitleiden.nl\/iiif_manifest\/item:335458\/canvas\/default\/annotation\/r32","type":"Annotation","motivation":"supplementing","body":{"text":"ᰠ ᰜᰤᰦᰵ ᰌᰦ ᰜᰩᰰ ᰍᰩᰰ ᰕ ᰣᰨ ᰼ ᰚᰨ ᰜ ᰓᰧ ᰓᰦᰵ ᰃᰬ","type":"TextualBody"},"target":"https:\/\/digitalcollections.universiteitleiden.nl\/iiif_manifest\/item:335458\/canvas\/default#xywh=3088,3384,2073,229"}},{"manifest":"m335412","canvas":"https:\/\/digitalcollections.universiteitleiden.nl\/iiif_manifest\/item:335458\/canvas\/default","mode":"line","line":"33","annotation":{"id":"https:\/\/digitalcollections.universiteitleiden.nl\/iiif_manifest\/item:335458\/canvas\/default\/annotation\/r33","type":"Annotation","motivation":"supplementing","body":{"text":"ᰛᰬ ᰓᰫᰵ ᰜ ᰕ ᰃᰧᰰᰶ ᰍ ᰅᰦ ᰜᰪᰵ ᰜᰧ ᰀᰦ ᰜᰩ ᰍᰩᰰ ᰡᰴ ᰕᰦᰳ","type":"TextualBody"},"target":"https:\/\/digitalcollections.universiteitleiden.nl\/iiif_manifest\/item:335458\/canvas\/default#xywh=3105,3561,2110,240"}},{"manifest":"m335412","canvas":"https:\/\/digitalcollections.universiteitleiden.nl\/iiif_manifest\/item:335458\/canvas\/default","mode":"line","line":"34","annotation":{"id":"https:\/\/digitalcollections.universiteitleiden.nl\/iiif_manifest\/item:335458\/canvas\/default\/annotation\/r34","type":"Annotation","motivation":"supplementing","body":{"text":"ᰜᰪᰵ ᰅᰦᰰ ᰌᰧ ᰅᰬ ᰛᰦ ᰼ ᰛᰬ ᰣ ᰓᰦ ᰕᰨ ᰠ ᰎᰪᰰ ᰣᰤᰫᰭ","type":"TextualBody"},"target":"https:\/\/digitalcollections.universiteitleiden.nl\/iiif_manifest\/item:335458\/canvas\/default#xywh=3099,3809,2067,228"}}]}